Workbook

Sheet 📋 Instructions
B1: EFL — Executive Scorecard
B3: PURPOSE | C3: This workbook collects all raw data needed to calculate the 8 scorecard metrics and automatically computes status (Green/Yellow/Red).
B4: HOW TO USE | C4: 1. Each month/sprint: open the relevant DATA INPUT sheet and enter blue-text cells only.
C5: 2. The SCORECARD sheet pulls all computed metrics automatically — do not edit it.
C6: 3. The Formulas sheet is a reference for all metric definitions and thresholds.
B7: COLOR CODING | C7: Blue = Input cells (you fill these) | Black = Formula (auto-calculated) | Green = Cross-sheet link
B9: SHEETS
B10: 💵 Financial | C10: Enter monthly cost actuals, planned spend, story points, and EAC updates.
B11: 🏃 Sprints | C11: AUTO-CALCULATED - Pull all data from 'Team Sprints Input' sheet and 'Team Median Input'
B12: 🏃 Team Sprints Input | C12: Enterp per-sprint commitment and completion counts for each delivery teams.
B13: Team Median Input | C13: Enterp per-sprint median cycle time (Dev, QA and Overall) for each delivery teams.
B14: 🐛 Quality | C14: Enter defect counts by severity per release; enter rework effort and first time pass rate
B15: 📊 Scorecard | C15: AUTO-CALCULATED. All 7 metrics with RAG status and 3-month/3-sprint trend.
B16: 📐 Formulas | C16: Reference sheet with all metric definitions and threshold rules.
B18: FREQUENCY | C18: Financial & Quality = Monthly. Sprint metrics = Per sprint + monthly rollup.
B19: BASELINE | C19: Set baselines in the yellow-highlighted cells on the Financial and Sprint sheets on first use.

Sheet 📊 Scorecard
A1: EXECUTIVE SCORECARD — Auto-Calculated Summary
A2: All values pull automatically from the data input sheets. Do not edit this sheet.
A4: Metric | B4: Jan | C4: Feb | D4: Mar | E4: Apr | F4: May | G4: Jun | H4: Threshold / Target
A5: 💰 FINANCIAL HEALTH
A6: EAC vs SOW Budget % | B6: ='💵 Financial'!B8 -> 0.88415506 | C6: ='💵 Financial'!C8 -> 0.91358829 | D6: ='💵 Financial'!D8 -> 0.80146837 | E6: ='💵 Financial'!E8 -> 0.82033534 | F6: ='💵 Financial'!F8 -> 0.75294014 | G6: ='💵 Financial'!G8 -> 0.93200612 | H6: 🟢 ≤100% 🟡 100–105% 🔴 >105%
A7: EAC Status | B7: ='💵 Financial'!B9 -> 🟢 Green | C7: ='💵 Financial'!C9 -> 🟢 Green | D7: ='💵 Financial'!D9 -> 🟢 Green | E7: ='💵 Financial'!E9 -> 🟢 Green | F7: ='💵 Financial'!F9 -> 🟢 Green | G7: ='💵 Financial'!G9 -> 🟢 Green | H7: Auto from Financial sheet
A9: Monthly Burn Variance % | B9: ='💵 Financial'!B16 -> -0.047594877 | C9: =AVERAGE('💵 Financial'!C16,'💵 Financial'!D16) -> -0.040488615 | D9: =AVERAGE('💵 Financial'!E16,'💵 Financial'!G16) -> -0.12745968 | E9: =AVERAGE('💵 Financial'!H16,'💵 Financial'!I16) -> -0.096597042 | F9: =AVERAGE('💵 Financial'!H16,'💵 Financial'!J16) -> -0.12138979 | G9: =AVERAGE('💵 Financial'!I16,'💵 Financial'!K16) -> -0.32306728 | H9: 🟢 ≤±5% 🟡 ±5–10% 🔴 >±10%
A10: Burn Variance Status | B10: ='💵 Financial'!B17 -> 🟢 Green | C10: =IF(C9="","",IF(ABS(C9)<=0.05,"🟢 Green",IF(ABS(C9)<=0.1,"🟡 Yellow","🔴 Red"))) -> 🟢 Green | D10: =IF(D9="","",IF(ABS(D9)<=0.05,"🟢 Green",IF(ABS(D9)<=0.1,"🟡 Yellow","🔴 Red"))) -> 🔴 Red | E10: =IF(E9="","",IF(ABS(E9)<=0.05,"🟢 Green",IF(ABS(E9)<=0.1,"🟡 Yellow","🔴 Red"))) -> 🟡 Yellow | F10: =IF(F9="","",IF(ABS(F9)<=0.05,"🟢 Green",IF(ABS(F9)<=0.1,"🟡 Yellow","🔴 Red"))) -> 🔴 Red | G10: =IF(G9="","",IF(ABS(G9)<=0.05,"🟢 Green",IF(ABS(G9)<=0.1,"🟡 Yellow","🔴 Red"))) -> 🔴 Red | H10: Auto from Financial sheet
A12: Cost per SP — Stories Delivered($) | B12: ='💵 Financial'!B43 -> 2281.4432 | C12: ='💵 Financial'!B44 -> 979.39367 | D12: ='💵 Financial'!B45 -> 880.60686 | E12: ='💵 Financial'!B46 -> 835.65969 | F12: ='💵 Financial'!B47 -> 593.01262 | G12: ='💵 Financial'!B48 -> 526.12919 | H12: 🟢 Stable/↓ 🟡 ↑5–10% 🔴 ↑>10%
A13: Cost/SP Status | B13: NIL | C13: ='💵 Financial'!E44 -> 🟢 Green | D13: ='💵 Financial'!E45 -> 🟢 Green | E13: ='💵 Financial'!E46 -> 🟢 Green | F13: ='💵 Financial'!E47 -> 🟢 Green | G13: ='💵 Financial'!E48 -> 🟢 Green | H13: Auto from Financial sheet
A14: 3-Mo Rolling Avg Cost/SP ($) | B14: ='💵 Financial'!B29 -> NIL | C14: ='💵 Financial'!D29 -> 979.39367 | D14: ='💵 Financial'!G29 -> 920.12159 | E14: ='💵 Financial'!H29 -> 892.33755 | F14: ='💵 Financial'!J29 -> 872.43325 | G14: ='💵 Financial'!L29 -> 794.82528 | H14: Trend indicator
A16: 🏃 DELIVERY PREDICTABILITY & FLOW
A17: Commitment Reliability — Monthly Avg | B17: ='🏃 Sprints'!C21 -> 1 | C17: ='🏃 Sprints'!C22 -> 0.97943038 | D17: ='🏃 Sprints'!C23 -> 1.0559072 | E17: ='🏃 Sprints'!C24 -> 0.86234177 | F17: ='🏃 Sprints'!C25 -> 0.42052176 | G17: ='🏃 Sprints'!I21 -> 0.47904476 | H17: 🟢 ≥85% 🟡 75–84% 🔴 <75%
A18: CR Status | B18: ='🏃 Sprints'!D21 -> 🟢 Green | C18: ='🏃 Sprints'!D22 -> 🟢 Green | D18: ='🏃 Sprints'!D23 -> 🟢 Green | E18: ='🏃 Sprints'!D24 -> 🟢 Green | F18: ='🏃 Sprints'!D25 -> 🔴 Red | G18: ='🏃 Sprints'!J21 -> 🔴 Red | H18: Auto from Sprints sheet
A20: Cycle Time Median | B20: ='🏃 Sprints'!C30 -> 5.3 | C20: =AVERAGE('🏃 Sprints'!C31,'🏃 Sprints'!C32) -> 4.52875 | D20: =AVERAGE('🏃 Sprints'!C33,'🏃 Sprints'!C35) -> 5.1825 | E20: =AVERAGE('🏃 Sprints'!C36,'🏃 Sprints'!C37) -> 4.5175 | F20: =AVERAGE('🏃 Sprints'!C38,'🏃 Sprints'!C39) -> 4.7345833 | G20: =AVERAGE('🏃 Sprints'!C40,'🏃 Sprints'!C41) -> 7.62 | H20: 🟢 Stable/↓ 🟡 ↑ up to 10% 🔴 ↑>10%
A21: Cycle Time Status | B21: ='🏃 Sprints'!G30 -> 🟢 Green | C21: =IF(AVERAGE('🏃 Sprints'!F31,'🏃 Sprints'!F32)<=0, "🟢 Green", IF(AVERAGE('🏃 Sprints'!F31,'🏃 Sprints'!F32)<=10%, "🟢 Yellow", "🔴 Red")) -> 🟢 Green | D21: =IF(AVERAGE('🏃 Sprints'!F33,'🏃 Sprints'!F35)<=0, "🟢 Green", IF(AVERAGE('🏃 Sprints'!F33,'🏃 Sprints'!F35)<=10%, "🟢 Yellow", "🔴 Red")) -> 🟢 Green | E21: =IF(AVERAGE('🏃 Sprints'!F36,'🏃 Sprints'!F37)<=0, "🟢 Green", IF(AVERAGE('🏃 Sprints'!F36,'🏃 Sprints'!F37)<=10%, "🟢 Yellow", "🔴 Red")) -> 🟢 Green | F21: =IF(AVERAGE('🏃 Sprints'!F38,'🏃 Sprints'!F39)<=0, "🟢 Green", IF(AVERAGE('🏃 Sprints'!F38,'🏃 Sprints'!F39)<=10%, "🟢 Yellow", "🔴 Red")) -> 🟢 Green | G21: =IF(AVERAGE('🏃 Sprints'!F40,'🏃 Sprints'!F41)<=0, "🟢 Green", IF(AVERAGE('🏃 Sprints'!F40,'🏃 Sprints'!F41)<=10%, "🟢 Yellow", "🔴 Red")) -> 🔴 Red | H21: Auto from Sprints sheet
A23: 🐛 QUALITY & REWORK
A24: Defect Leakage % — Monthly | D24: ='🐛 Quality'!D20 -> 0.17647059 | E24: ='🐛 Quality'!D21 -> 0.015228426 | F24: ='🐛 Quality'!D22 -> 0.025862069 | G24: ='🐛 Quality'!D23 -> 0.090909091 | H24: 🟢 ≤10% 🟡 11–15% 🔴 >15%
A25: Leakage Status | D25: ='🐛 Quality'!E20 -> 🔴 Red | E25: ='🐛 Quality'!E21 -> 🟢 Green | F25: ='🐛 Quality'!E22 -> 🟢 Green | G25: ='🐛 Quality'!E23 -> 🟢 Green | H25: Auto from Quality sheet
A27: Rework Ratio — Monthly | B27: ='🐛 Quality'!E28 -> 0.034482759 | C27: =AVERAGE('🐛 Quality'!E29:E30) -> 0.21649781 | D27: =AVERAGE('🐛 Quality'!E31:E33) -> 0.21502271 | E27: =AVERAGE('🐛 Quality'!E34:E35) -> 0.2745463 | F27: =AVERAGE('🐛 Quality'!E36:E37) -> 0.27676394 | G27: =AVERAGE('🐛 Quality'!E38:E39) -> 0.34473092 | H27: Auto from Quality sheet
A28: Rework Status | B28: =IF(B27="","",IF(B27<=0.2,"🟢 Green",IF(B27<=0.3,"🟡 Yellow","🔴 Red"))) -> 🟢 Green | C28: =IF(C27="","",IF(C27<=0.2,"🟢 Green",IF(C27<=0.3,"🟡 Yellow","🔴 Red"))) -> 🟡 Yellow | D28: =IF(D27="","",IF(D27<=0.2,"🟢 Green",IF(D27<=0.3,"🟡 Yellow","🔴 Red"))) -> 🟡 Yellow | E28: =IF(E27="","",IF(E27<=0.2,"🟢 Green",IF(E27<=0.3,"🟡 Yellow","🔴 Red"))) -> 🟡 Yellow | F28: =IF(F27="","",IF(F27<=0.2,"🟢 Green",IF(F27<=0.3,"🟡 Yellow","🔴 Red"))) -> 🟡 Yellow | G28: =IF(G27="","",IF(G27<=0.2,"🟢 Green",IF(G27<=0.3,"🟡 Yellow","🔴 Red"))) -> 🔴 Red | H28: 🟢 ≤20% 🟡 21–30% 🔴 >30%
A30: First Time Pass Rate | D30: =AVERAGE('🐛 Quality'!E51:E52) -> 0.86363636 | E30: =AVERAGE('🐛 Quality'!E53:E54) -> 0.82600437 | F30: =AVERAGE('🐛 Quality'!E55:E56) -> 0.82620663 | G30: =AVERAGE('🐛 Quality'!E57:E58) -> 0.82205882
A31: Status | D31: =IF(D30="","",IF(D30>=95%,"🟢 Green",IF(D30>85%,"🟡 Yellow","🔴 Red"))) -> 🟡 Yellow | E31: =IF(E30="","",IF(E30>=95%,"🟢 Green",IF(E30>85%,"🟡 Yellow","🔴 Red"))) -> 🔴 Red | F31: =IF(F30="","",IF(F30>=95%,"🟢 Green",IF(F30>85%,"🟡 Yellow","🔴 Red"))) -> 🔴 Red | G31: =IF(G30="","",IF(G30>=95%,"🟢 Green",IF(G30>85%,"🟡 Yellow","🔴 Red"))) -> 🔴 Red | H31: >=95% : Green, >85% : Yellow, <=85% Red
A33: 📋 CURRENT MONTH SNAPSHOT — All Metrics at a Glance
A34: Metric | B34: Current Value | C34: Target | D34: Status | E34: Remarks
A35: EAC vs Budget | B35: =G6 -> 0.93200612 | C35: ≤100% | D35: =F7 -> 🟢 Green | E35: this is for June month
A36: Monthly Burn Variance | B36: =G9 -> -0.32306728 | C36: ±5% | D36: =G10 -> 🔴 Red | E36: 3 Onsite positions removed (Lalitha, Anil, Nanda) and rest all PTOs
A37: Cost/SP — Team | B37: =G12 -> 526.12919 | C37: 983 | D37: =G13 -> 🟢 Green
A38: Commitment Reliability | B38: =G17 -> 0.47904476 | C38: ≥85% | D38: =G18 -> 🔴 Red | E38: Overall red combining Q2 SP3, SP4 but SP2 commitment
A39: Cycle Time (Median) | B39: =G20 -> 7.62 | C39: 5.4 days | D39: =G21 -> 🔴 Red
A40: Prod Defect Leakage | B40: =G24 -> 0.090909091 | C40: ≤10% | D40: =G25 -> 🟢 Green
A41: Rework Ratio | B41: =G27 -> 0.34473092 | C41: ≤20% | D41: =G28 -> 🔴 Red | E41: this covers Q2 SP5 and Q2 SP6. Team 1 rework ratio was high 50%
A42: FTPR | B42: =G30 -> 0.82205882 | C42: >=95% | D42: =G31 -> 🔴 Red | E42: Team 1 and Team 2 had low FTPR consistently for both sprints

Sheet 💵 Financial
A1: FINANCIAL DATA INPUT — Monthly
A2: Blue cells = enter data. Black cells = auto-calculated. Update monthly.
A4: SECTION A — Budget & EAC
A5: Field | B5: Jan | C5: Feb | D5: Mar | E5: Apr | F5: May | G5: Jun | H5: July | J5: Notes
A6: SOW Budget Target ($) | B6: 471406 | C6: 471406 | D6: 471406 | E6: 471406 | F6: 471406 | G6: 399308 | J6: Enter SOW contract value
A7: Estimate at Completion EAC ($) | B7: 416796 | C7: 430671 | D7: 377817 | E7: 386711 | F7: 354940.5 | G7: 372157.5 | J7: Enter latest EAC each month
A8: EAC vs Budget % | B8: =B7/B6 -> 0.88415506 | C8: =C7/C6 -> 0.91358829 | D8: =D7/D6 -> 0.80146837 | E8: =E7/E6 -> 0.82033534 | F8: =IFERROR(F7/F6,"") -> 0.75294014 | G8: =IFERROR(G7/G6,"") -> 0.93200612 | J8: Auto: EAC÷Budget
A9: EAC Status | B9: =IF(B8="","",IF(B8<=1,"🟢 Green",IF(B8<=1.05,"🟡 Yellow","🔴 Red"))) -> 🟢 Green | C9: =IF(C8="","",IF(C8<=1,"🟢 Green",IF(C8<=1.05,"🟡 Yellow","🔴 Red"))) -> 🟢 Green | D9: =IF(D8="","",IF(D8<=1,"🟢 Green",IF(D8<=1.05,"🟡 Yellow","🔴 Red"))) -> 🟢 Green | E9: =IF(E8="","",IF(E8<=1,"🟢 Green",IF(E8<=1.05,"🟡 Yellow","🔴 Red"))) -> 🟢 Green | F9: =IF(F8="","",IF(F8<=1,"🟢 Green",IF(F8<=1.05,"🟡 Yellow","🔴 Red"))) -> 🟢 Green | G9: =IF(G8="","",IF(G8<=1,"🟢 Green",IF(G8<=1.05,"🟡 Yellow","🔴 Red"))) -> 🟢 Green | J9: Auto: RAG threshold ≤100%/≤105%/>105%
A11: SECTION B — Sprint Burn Variance (Exclude VM DM cost and Innova/ERIE cost)
A12: Field | B12: SP1 | C12: SP2 | D12: SP3 | E12: SP4 | F12: SP5 | G12: SP6 | H12: Q2 SP1 | I12: Q2 SP2 | J12: Q2 SP3 | K12: Q2 SP4 | L12: Q2 SP5 | M12: Q2 SP6 | N12: Notes
A13: Planned Monthly Spend ($) | B13: 210800 | C13: 210800 | D13: 210800 | E13: 210800 | F13: 210800 | G13: 210800 | H13: 210800 | I13: 192960 | J13: 190960 | K13: 190960 | L13: 190560 | M13: 190560 | N13: Enter planned budget for given sprint | Q13: ERIE | R13: Colton, John, Luke, Jacob, Marc, Jen, Erin, Matt, Sierra, Ryan, Mru
A14: Actual Monthly Spend ($) | B14: 200767 | C14: 195257 | D14: 209273 | E14: 198914 | F14: 182912 | G14: 168949 | H14: 182327 | I14: 181744.6 | J14: 170392 | K14: 78673.3 | L14: 156786.5 | M14: 167721.6 | N14: Enter actual spend | Q14: Innova | R14: 4 onsite (2 Mendix + 1 Integration + 1 BA), 4 offshore (2 Mendix + 2 QA)
A15: Burn Variance ($) | B15: =IF(B14="","",B14-B13) -> -10033 | C15: =IF(C14="","",C14-C13) -> -15543 | D15: =IF(D14="","",D14-D13) -> -1527 | E15: =IF(E14="","",E14-E13) -> -11886 | F15: =IF(F14="","",F14-F13) -> -27888 | G15: =IF(G14="","",G14-G13) -> -41851 | H15: =IF(H14="","",H14-H13) -> -28473 | I15: =IF(I14="","",I14-I13) -> -11215.4 | ... M15: =IF(M14="","",M14-M13) -> -22838.4 | N15: Auto: Actual−Planned
A16: Burn Variance % | B16: =IFERROR(IF(B15="","",B15/B13),"") -> -0.047594877 | C16: =IFERROR(IF(C15="","",C15/C13),"") -> -0.073733397 | D16: =IFERROR(IF(D15="","",D15/D13),"") -> -0.007243833 | E16: =IFERROR(IF(E15="","",E15/E13),"") -> -0.056385199 | F16: =IFERROR(IF(F15="","",F15/F13),"") -> -0.13229602 | G16: =IFERROR(IF(G15="","",G15/G13),"") -> -0.19853416 | H16: =IFERROR(IF(H15="","",H15/H13),"") -> -0.13507116 | I16: =IFERROR(IF(I15="","",I15/I13),"") -> -0.058122927 | ... M16: =IFERROR(IF(M15="","",M15/M13),"") -> -0.11984887 | N16: Auto: Variance÷Planned
A17: Burn Status | B17: =IF(B16="","",IF(ABS(B16)<=0.05,"🟢 Green",IF(ABS(B16)<=0.1,"🟡 Yellow","🔴 Red"))) -> 🟢 Green | C17: =IF(C16="","",IF(ABS(C16)<=0.05,"🟢 Green",IF(ABS(C16)<=0.1,"🟡 Yellow","🔴 Red"))) -> 🟡 Yellow | D17: =IF(D16="","",IF(ABS(D16)<=0.05,"🟢 Green",IF(ABS(D16)<=0.1,"🟡 Yellow","🔴 Red"))) -> 🟢 Green | E17: =IF(E16="","",IF(ABS(E16)<=0.05,"🟢 Green",IF(ABS(E16)<=0.1,"🟡 Yellow","🔴 Red"))) -> 🟡 Yellow | F17: =IF(F16="","",IF(ABS(F16)<=0.05,"🟢 Green",IF(ABS(F16)<=0.1,"🟡 Yellow","🔴 Red"))) -> 🔴 Red | G17: =IF(G16="","",IF(ABS(G16)<=0.05,"🟢 Green",IF(ABS(G16)<=0.1,"🟡 Yellow","🔴 Red"))) -> 🔴 Red | H17: =IF(H16="","",IF(ABS(H16)<=0.05,"🟢 Green",IF(ABS(H16)<=0.1,"🟡 Yellow","🔴 Red"))) -> 🔴 Red | I17: =IF(I16="","",IF(ABS(I16)<=0.05,"🟢 Green",IF(ABS(I16)<=0.1,"🟡 Yellow","🔴 Red"))) -> 🟡 Yellow | ... M17: =IF(M16="","",IF(ABS(M16)<=0.05,"🟢 Green",IF(ABS(M16)<=0.1,"🟡 Yellow","🔴 Red"))) -> 🔴 Red | N17: Auto: RAG ≤±5% / ≤±10% / >±10%
A19: SECTION C — Cost per Story Point (Only VM)
A20: Field | B20: SP1 | C20: SP2 | D20: SP3 | E20: SP4 | F20: SP5 | G20: SP6 | H20: Q2 SP1 | I20: Q2 SP2 | J20: Q2 SP3 | K20: Q2 SP4 | L20: Q2 SP5 | M20: Q2 SP6 | N20: Notes
A21: Story Points Delivered (All 4 Teams) | B21: ='🏃 Sprints'!N5 -> 84 | C21: ='🏃 Sprints'!N6 -> 178 | D21: ='🏃 Sprints'!N7 -> 147 | E21: ='🏃 Sprints'!N8 -> 323 | F21: ='🏃 Sprints'!N9 -> 164 | G21: ='🏃 Sprints'!N10 -> 113 | H21: ='🏃 Sprints'!N11 -> 220 | I21: ='🏃 Sprints'!N12 -> 141 | J21: ='🏃 Sprints'!N13 -> 169 | K21: ='🏃 Sprints'!N14 -> 162 | L21: ='🏃 Sprints'!N15 -> 215 | M21: ='🏃 Sprints'!N16 -> 135 | N21: Feature+story SP completed
A22: Defect (bugs) SP Delivered (All 4 Teams) | B22: ='🏃 Sprints'!O5 -> 4 | C22: ='🏃 Sprints'!O6 -> 22 | D22: ='🏃 Sprints'!O7 -> 66 | E22: ='🏃 Sprints'!O8 -> 108 | F22: ='🏃 Sprints'!O9 -> 37 | G22: ='🏃 Sprints'!O10 -> 20 | H22: ='🏃 Sprints'!O11 -> 22 | I22: ='🏃 Sprints'!O12 -> 57 | J22: ='🏃 Sprints'!O13 -> 41 | K22: ='🏃 Sprints'!O14 -> 48 | L22: ='🏃 Sprints'!O15 -> 83 | M22: ='🏃 Sprints'!O16 -> 50 | N22: Defect SP completed this month
A23: Total SP (incl. Defects) | B23: =IF(B21="","",B21+B22) -> 88 | C23: =IF(C21="","",C21+C22) -> 200 | D23: =IF(D21="","",D21+D22) -> 213 | E23: =IF(E21="","",E21+E22) -> 431 | F23: =IF(F21="","",F21+F22) -> 201 | G23: =IF(G21="","",G21+G22) -> 133 | H23: =IF(H21="","",H21+H22) -> 242 | I23: =IF(I21="","",I21+I22) -> 198 | ... M23: =IF(M21="","",M21+M22) -> 185 | N23: Auto: sum
A24: Team Cost ($) (from Actual Burn) | B24: =B14 -> 200767 | C24: =C14 -> 195257 | D24: =D14 -> 209273 | E24: =E14 -> 198914 | F24: =F14 -> 182912 | G24: =G14 -> 168949 | H24: =H14 -> 182327 | I24: =I14 -> 181744.6 | ... M24: =M14 -> 167721.6 | N24: Auto: links from Actual Spend above
A25: Cost per SP — Stories Completed ($) | B25: =IFERROR(IF(B21="","",B24/B21),"") -> 2390.0833 | C25: =IFERROR(IF(C21="","",C24/C21),"") -> 1096.9494 | D25: =IFERROR(IF(D21="","",D24/D21),"") -> 1423.6259 | E25: =IFERROR(IF(E21="","",E24/E21),"") -> 615.83282 | F25: =IFERROR(IF(F21="","",F24/F21),"") -> 1115.3171 | G25: =IFERROR(IF(G21="","",G24/G21),"") -> 1495.1239 | H25: =IFERROR(IF(H21="","",H24/H21),"") -> 828.75909 | I25: =IFERROR(IF(I21="","",I24/I21),"") -> 1288.9688 | ... M25: =IFERROR(IF(M21="","",M24/M21),"") -> 1242.3822 | N25: Auto: Team Cost ÷ Stories SP
A26: Cost per SP — Stories + Standalone Defects ($) | B26: =IFERROR(IF(B23="","",B24/B23),"") -> 2281.4432 | C26: =IFERROR(IF(C23="","",C24/C23),"") -> 976.285 | D26: =IFERROR(IF(D23="","",D24/D23),"") -> 982.50235 | E26: =IFERROR(IF(E23="","",E24/E23),"") -> 461.5174 | F26: =IFERROR(IF(F23="","",F24/F23),"") -> 910.00995 | G26: =IFERROR(IF(G23="","",G24/G23),"") -> 1270.2932 | H26: =IFERROR(IF(H23="","",H24/H23),"") -> 753.41736 | I26: =IFERROR(IF(I23="","",I24/I23),"") -> 917.90202 | ... M26: =IFERROR(IF(M23="","",M24/M23),"") -> 906.60324 | N26: Auto: Team Cost ÷ Total SP
A27: Baseline Cost/SP — Team ($) | B27: NIL | C27: NIL | D27: 983 | E27: 983 | F27: 983 | G27: 983 | H27: 983 | I27: 983 | J27: 983 | K27: 983 | L27: 983 | M27: 983 | N27: 🟡 Set once based on 2-3 Sprints
A28: Team Cost/SP Status | B28: =IF(B25="","",IF(B25<=B27,"🟢 Green",IF(B25<=B27*1.1,"🟡 Yellow","🔴 Red"))) -> 🟢 Green | C28: =IF(C25="","",IF(C25<=C27,"🟢 Green",IF(C25<=C27*1.1,"🟡 Yellow","🔴 Red"))) -> 🟢 Green | D28: =IF(D26="","",IF(D26<=D27,"🟢 Green",IF(D26<=D27*1.1,"🟡 Yellow","🔴 Red"))) -> 🟢 Green | E28: =IF(E26="","",IF(E26<=E27,"🟢 Green",IF(E26<=E27*1.1,"🟡 Yellow","🔴 Red"))) -> 🟢 Green | F28: =IF(F26="","",IF(F26<=F27,"🟢 Green",IF(F26<=F27*1.1,"🟡 Yellow","🔴 Red"))) -> 🟢 Green | G28: =IF(G26="","",IF(G26<=G27,"🟢 Green",IF(G26<=G27*1.1,"🟡 Yellow","🔴 Red"))) -> 🔴 Red | H28: =IF(H25="","",IF(H25<=H27,"🟢 Green",IF(H25<=H27*1.1,"🟡 Yellow","🔴 Red"))) -> 🟢 Green | I28: =IF(I25="","",IF(I25<=I27,"🟢 Green",IF(I25<=I27*1.1,"🟡 Yellow","🔴 Red"))) -> 🔴 Red | J28: =IF(J25="","",IF(J25<=J27,"🟢 Green",IF(J25<=J27*1.1,"🟡 Yellow","🔴 Red"))) -> 🟡 Yellow | K28: =IF(K25="","",IF(K25<=K27,"🟢 Green",IF(K25<=K27*1.1,"🟡 Yellow","🔴 Red"))) -> 🟢 Green | L28: =IF(L25="","",IF(L25<=L27,"🟢 Green",IF(L25<=L27*1.1,"🟡 Yellow","🔴 Red"))) -> 🟢 Green | M28: =IF(M25="","",IF(M25<=M27,"🟢 Green",IF(M25<=M27*1.1,"🟡 Yellow","🔴 Red"))) -> 🔴 Red | N28: Auto: RAG vs baseline ±10% (Variance <=10% Yellow, >10% Red)
A29: 3-Month Rolling Avg Cost/SP — Team ($) | B29: NIL | C29: =IFERROR(AVERAGE(C26:C26),"") -> 976.285 | D29: =IFERROR(AVERAGE(C26:D26),"") -> 979.39367 | E29: =IFERROR(AVERAGE(C26:E26),"") -> 806.76825 | F29: =IFERROR(AVERAGE(C26:F26),"") -> 832.57867 | G29: =IFERROR(AVERAGE(C26:G26),"") -> 920.12159 | H29: =IFERROR(AVERAGE(C26:H26),"") -> 892.33755 | I29: =IFERROR(AVERAGE(C26:I26),"") -> 895.98962 | J29: =IFERROR(AVERAGE(D26:J26),"") -> 872.43325 | K29: =IFERROR(AVERAGE(E26:K26),"") -> 785.59503 | L29: =IFERROR(AVERAGE(F26:L26),"") -> 794.82528 | M29: =IFERROR(AVERAGE(G26:M26),"") -> 794.33861 | N29: Auto: rolling 3-month avg (for trend reporting)
A32: MONTHLY ROLLUP — Budget & EAC
A33: Month | B33: Budget | C33: Actual | D33: Variance ($) | E33: Variance % | F33: 3-Sprint Trend
A34: January | B34: =B6 -> 471406 | C34: =B7 -> 416796 | D34: =B34-C34 -> 54610 | E34: =C34/B34 -> 0.88415506 | F34: =IF(E34="","",IF(E34<=1,"🟢 Green",IF(E34<=1.05,"🟡 Yellow","🔴 Red"))) -> 🟢 Green
A35: February | B35: =B6+C6 -> 942812 | C35: =B7+C7 -> 847467 | D35: =B35-C35 -> 95345 | E35: =C35/B35 -> 0.89887167 | F35: =IF(E35="","",IF(E35<=1,"🟢 Green",IF(E35<=1.05,"🟡 Yellow","🔴 Red"))) -> 🟢 Green
A36: March | B36: =B35+D6 -> 1414218 | C36: =C35+D7 -> 1225284 | D36: =B36-C36 -> 188934 | E36: =C36/B36 -> 0.86640391 | F36: =IF(E36="","",IF(E36<=1,"🟢 Green",IF(E36<=1.05,"🟡 Yellow","🔴 Red"))) -> 🟢 Green
A37: April | B37: =B36+E6 -> 1885624 | C37: =C36+E7 -> 1611995 | D37: =B37-C37 -> 273629 | E37: =C37/B37 -> 0.85488676 | F37: =IF(E37="","",IF(E37<=1,"🟢 Green",IF(E37<=1.05,"🟡 Yellow","🔴 Red"))) -> 🟢 Green
A38: May | B38: =B37+F6 -> 2357030 | C38: =C37+F7 -> 1966935.5 | D38: =B38-C38 -> 390094.5 | E38: =C38/B38 -> 0.83449744 | F38: =IF(E38="","",IF(E38<=1,"🟢 Green",IF(E38<=1.05,"🟡 Yellow","🔴 Red"))) -> 🟢 Green
A39: June | B39: =B38+G6 -> 2756338 | C39: =C38+G7 -> 2339093 | D39: =B39-C39 -> 417245 | E39: =C39/B39 -> 0.84862343 | F39: =IF(E39="","",IF(E39<=1,"🟢 Green",IF(E39<=1.05,"🟡 Yellow","🔴 Red"))) -> 🟢 Green
A41: MONTHLY ROLLUP — Cost per Story Point
A42: Month | B42: Actual | C42: Baseline | D42: Variance % | E42: Trend
A43: January | B43: =B26 -> 2281.4432 | C43: =B27 -> NIL | D43: =(B43-C43)/C43 -> #VALUE! | E43: =IF(B43="","",IF(B43<=C43,"🟢 Green",IF(B43<=C43*1.1,"🟡 Yellow","🔴 Red"))) -> 🟢 Green
A44: February | B44: =AVERAGE(C26:D26) -> 979.39367 | C44: =D27 -> 983 | D44: =((B44-C44)/C44) -> -0.0036686941 | E44: =IF(B44="","",IF(B44<=C44,"🟢 Green",IF(B44<=C44*1.1,"🟡 Yellow","🔴 Red"))) -> 🟢 Green
A45: March | B45: =AVERAGE(E26:G26) -> 880.60686 | C45: =D27 -> 983 | D45: =((B45-C45)/C45) -> -0.10416393 | E45: =IF(B45="","",IF(B45<=C45,"🟢 Green",IF(B45<=C45*1.1,"🟡 Yellow","🔴 Red"))) -> 🟢 Green
A46: April | B46: =AVERAGE(H26:I26) -> 835.65969 | C46: =D27 -> 983 | D46: =((B46-C46)/C46) -> -0.14988842 | E46: =IF(B46="","",IF(B46<=C46,"🟢 Green",IF(B46<=C46*1.1,"🟡 Yellow","🔴 Red"))) -> 🟢 Green
A47: May | B47: =AVERAGE(J26:K26) -> 593.01262 | C47: =J27 -> 983 | D47: =((B47-C47)/C47) -> -0.39673182 | E47: =IF(B47="","",IF(B47<=C47,"🟢 Green",IF(B47<=C47*1.1,"🟡 Yellow","🔴 Red"))) -> 🟢 Green
A48: June | B48: =AVERAGE(L26) -> 526.12919 | C48: =J27 -> 983 | D48: =((B48-C48)/C48) -> -0.46477193 | E48: =IF(B48="","",IF(B48<=C48,"🟢 Green",IF(B48<=C48*1.1,"🟡 Yellow","🔴 Red"))) -> 🟢 Green

Sheet 🐛 Quality
A1: QUALITY DATA INPUT — Monthly & Per Release
B2: Enter defect data per release. Enter effort hours monthly. Status is auto-calculated.
A4: SECTION A — Production Defect Leakage (Per Release) - 0–10% : Green 11–15% : Yellow, 15%> : Red
B5: Formula: Prod Defect / All Defects X 100 | Sev1=5× Sev2=3× Sev3=1×
A6: Release / Feature | B6: Month | C6: Prod Defects Sev 1 (#) | D6: Prod Defects Sev 2 (#) | E6: Prod Defects Sev 3 (#) | F6: Prod Defects Sev 4 (#) | G6: Prod Defects Sev 5 (#) | H6: Total Prod Defects | I6: QA Defects | J6: UAT Defects | K6: Total Defects | L6: Leakage % (auto) | M6: Leakage Status
A7: EEL STOLI Release | B7: March | C7: 0 | F7: 2 | G7: 1 | H7: =SUM(C7:G7) -> 3 | I7: 17 | J7: 0 | K7: =SUM(I7:J7) -> 17 | L7: =SUM(C7:G7)/K7 -> 0.17647059 | M7: =IF(L7="","",IF(L7<=0.1,"🟢 Green",IF(L7<=0.15,"🟡 Yellow","🔴 Red"))) -> 🔴 Red
A8: TUW Pilot | B8: April | D8: 1 | E8: 3 | F8: 5 | H8: =SUM(C8:G8) -> 9 | I8: 573 | J8: 18 | K8: =SUM(I8:J8) -> 591 | L8: =SUM(C8:G8)/K8 -> 0.015228426 | M8: =IF(L8="","",IF(L8<=0.1,"🟢 Green",IF(L8<=0.15,"🟡 Yellow","🔴 Red"))) -> 🟢 Green
A9: TUW 1.1 | B9: May | D9: 2 | E9: 1 | H9: =SUM(C9:G9) -> 3 | I9: 93 | J9: 23 | K9: =SUM(I9:J9) -> 116 | L9: =SUM(C9:G9)/K9 -> 0.025862069 | M9: =IF(L9="","",IF(L9<=0.1,"🟢 Green",IF(L9<=0.15,"🟡 Yellow","🔴 Red"))) -> 🟢 Green
A10: TUW 1.3 | B10: June | D10: 4 | E10: 14 | F10: 3 | H10: =SUM(C10:G10) -> 21 | I10: 229 | J10: 2 | K10: =SUM(I10:J10) -> 231 | L10: =IFERROR(IF(SUM(C10:J10)=0,"",(C10*5+D10*3+E10*1)/(C10*5+D10*3+E10*1+H10*5+I10*3+J10*1)),"") -> 0.031707317 | M10: =IF(L10="","",IF(L10<=0.1,"🟢 Green",IF(L10<=0.15,"🟡 Yellow","🔴 Red"))) -> 🟢 Green
L11: =IFERROR(IF(SUM(C11:J11)=0,"",(C11*5+D11*3+E11*1)/(C11*5+D11*3+E11*1+H11*5+I11*3+J11*1)),"") | M11: =IF(L11="","",IF(L11<=0.1,"🟢 Green",IF(L11<=0.15,"🟡 Yellow","🔴 Red")))
L12: =IFERROR(IF(SUM(C12:J12)=0,"",(C12*5+D12*3+E12*1)/(C12*5+D12*3+E12*1+H12*5+I12*3+J12*1)),"") | M12: =IF(L12="","",IF(L12<=0.1,"🟢 Green",IF(L12<=0.15,"🟡 Yellow","🔴 Red")))
L13: =IFERROR(IF(SUM(C13:J13)=0,"",(C13*5+D13*3+E13*1)/(C13*5+D13*3+E13*1+H13*5+I13*3+J13*1)),"") | M13: =IF(L13="","",IF(L13<=0.1,"🟢 Green",IF(L13<=0.15,"🟡 Yellow","🔴 Red")))
L14: =IFERROR(IF(SUM(C14:J14)=0,"",(C14*5+D14*3+E14*1)/(C14*5+D14*3+E14*1+H14*5+I14*3+J14*1)),"") | M14: =IF(L14="","",IF(L14<=0.1,"🟢 Green",IF(L14<=0.15,"🟡 Yellow","🔴 Red")))
L15: =IFERROR(IF(SUM(C15:J15)=0,"",(C15*5+D15*3+E15*1)/(C15*5+D15*3+E15*1+H15*5+I15*3+J15*1)),"") | M15: =IF(L15="","",IF(L15<=0.1,"🟢 Green",IF(L15<=0.15,"🟡 Yellow","🔴 Red")))
L16: =IFERROR(IF(SUM(C16:J16)=0,"",(C16*5+D16*3+E16*1)/(C16*5+D16*3+E16*1+H16*5+I16*3+J16*1)),"") | M16: =IF(L16="","",IF(L16<=0.1,"🟢 Green",IF(L16<=0.15,"🟡 Yellow","🔴 Red")))
A18: SECTION B — Monthly Defect Leakage Rollup - 0–10% : Green 11–15% : Yellow, 15%> : Red
A19: Month | B19: Total Prod Defects | C19: Total Pre-prod Defects | D19: Leakage % | E19: Status
A20: March | B20: =SUMPRODUCT((B7:B16=A20)*(H7:H16)) -> 3 | C20: =SUMPRODUCT((B7:B16=A20)*K7:K16) -> 17 | D20: =B20/C20 -> 0.17647059 | E20: =IF(D20="","",IF(D20<=0.1,"🟢 Green",IF(D20<=0.15,"🟡 Yellow","🔴 Red"))) -> 🔴 Red
A21: April | B21: =SUMPRODUCT((B8:B17=A21)*(H8:H17)) -> 9 | C21: =SUMPRODUCT((B8:B17=A21)*K8:K17) -> 591 | D21: =B21/C21 -> 0.015228426 | E21: =IF(D21="","",IF(D21<=0.1,"🟢 Green",IF(D21<=0.15,"🟡 Yellow","🔴 Red"))) -> 🟢 Green
A22: May | B22: =SUMPRODUCT((B9:B18=A22)*(H9:H18)) -> 3 | C22: =SUMPRODUCT((B9:B18=A22)*K9:K18) -> 116 | D22: =B22/C22 -> 0.025862069 | E22: =IF(D22="","",IF(D22<=0.1,"🟢 Green",IF(D22<=0.15,"🟡 Yellow","🔴 Red"))) -> 🟢 Green
A23: June | B23: =SUMPRODUCT((B10:B19=A23)*(H10:H19)) -> 21 | C23: =SUMPRODUCT((B10:B19=A23)*K10:K19) -> 231 | D23: =B23/C23 -> 0.090909091 | E23: =IF(D23="","",IF(D23<=0.1,"🟢 Green",IF(D23<=0.15,"🟡 Yellow","🔴 Red"))) -> 🟢 Green
A25: SECTION C — Rework Ratio (Sprint and Monthly View) - <=20% : Green, <=30% : Yellow, >30% Red
A26: Rework Ratio = Defect Effort in Points/ Total Completed Story Points × 100
A27: Sprint ID | B27: Month | C27: Rework # (Standalone Bugs) | D27: Total Completed | E27: Rework Ratio | F27: Status | G27: Notes | H27: Mitigation
A28: Sprint 1 | B28: January | C28: =IFERROR(SUMIFS('🏃 Sprints'!H:H,'🏃 Sprints'!A:A,$A28,'🏃 Sprints'!B:B,$B28),0) -> 4 | D28: =IFERROR(SUMIFS('🏃 Sprints'!J:J,'🏃 Sprints'!A:A,$A28,'🏃 Sprints'!B:B,$B28),0) -> 116 | E28: =C28/D28 -> 0.034482759 | F28: =IF(E28="","",IF(E28<=0.2,"🟢 Green",IF(E28<=0.3,"🟡 Yellow","🔴 Red"))) -> 🟢 Green
A29: Sprint 2 | B29: February | C29: =IFERROR(SUMIFS('🏃 Sprints'!H:H,'🏃 Sprints'!A:A,$A29,'🏃 Sprints'!B:B,$B29),0) -> 34 | D29: =IFERROR(SUMIFS('🏃 Sprints'!J:J,'🏃 Sprints'!A:A,$A29,'🏃 Sprints'!B:B,$B29),0) -> 404 | E29: =C29/D29 -> 0.084158416 | F29: =IF(E29="","",IF(E29<=0.2,"🟢 Green",IF(E29<=0.3,"🟡 Yellow","🔴 Red"))) -> 🟢 Green
A30: Sprint 3 | B30: February | C30: =IFERROR(SUMIFS('🏃 Sprints'!H:H,'🏃 Sprints'!A:A,$A30,'🏃 Sprints'!B:B,$B30),0) -> 75 | D30: =IFERROR(SUMIFS('🏃 Sprints'!J:J,'🏃 Sprints'!A:A,$A30,'🏃 Sprints'!B:B,$B30),0) -> 215 | E30: =C30/D30 -> 0.34883721 | F30: =IF(E30="","",IF(E30<=0.2,"🟢 Green",IF(E30<=0.3,"🟡 Yellow","🔴 Red"))) -> 🔴 Red
A31: Sprint 4 | B31: March | C31: =IFERROR(SUMIFS('🏃 Sprints'!H:H,'🏃 Sprints'!A:A,$A31,'🏃 Sprints'!B:B,$B31),0) -> 127 | D31: =IFERROR(SUMIFS('🏃 Sprints'!J:J,'🏃 Sprints'!A:A,$A31,'🏃 Sprints'!B:B,$B31),0) -> 439 | E31: =C31/D31 -> 0.28929385 | F31: =IF(E31="","",IF(E31<=0.2,"🟢 Green",IF(E31<=0.3,"🟡 Yellow","🔴 Red"))) -> 🟡 Yellow
A32: Sprint 5 | B32: March | C32: =IFERROR(SUMIFS('🏃 Sprints'!H:H,'🏃 Sprints'!A:A,$A32,'🏃 Sprints'!B:B,$B32),0) -> 60 | D32: =IFERROR(SUMIFS('🏃 Sprints'!J:J,'🏃 Sprints'!A:A,$A32,'🏃 Sprints'!B:B,$B32),0) -> 351 | E32: =C32/D32 -> 0.17094017 | F32: =IF(E32="","",IF(E32<=0.2,"🟢 Green",IF(E32<=0.3,"🟡 Yellow","🔴 Red"))) -> 🟢 Green
A33: Sprint 6 | B33: March | C33: =IFERROR(SUMIFS('🏃 Sprints'!H:H,'🏃 Sprints'!A:A,$A33,'🏃 Sprints'!B:B,$B33),0) -> 39 | D33: =IFERROR(SUMIFS('🏃 Sprints'!J:J,'🏃 Sprints'!A:A,$A33,'🏃 Sprints'!B:B,$B33),0) -> 211 | E33: =C33/D33 -> 0.18483412 | F33: =IF(E33="","",IF(E33<=0.2,"🟢 Green",IF(E33<=0.3,"🟡 Yellow","🔴 Red"))) -> 🟢 Green
A34: Q2 Sprint 1 | B34: April | C34: =IFERROR(SUMIFS('🏃 Sprints'!H:H,'🏃 Sprints'!A:A,$A34,'🏃 Sprints'!B:B,$B34),0) -> 37 | D34: =IFERROR(SUMIFS('🏃 Sprints'!J:J,'🏃 Sprints'!A:A,$A34,'🏃 Sprints'!B:B,$B34),0) -> 307 | E34: =C34/D34 -> 0.12052117 | F34: =IF(E34="","",IF(E34<=0.2,"🟢 Green",IF(E34<=0.3,"🟡 Yellow","🔴 Red"))) -> 🟢 Green
A35: Q2 Sprint 2 | B35: April | C35: =IFERROR(SUMIFS('🏃 Sprints'!H:H,'🏃 Sprints'!A:A,$A35,'🏃 Sprints'!B:B,$B35),0) -> 102 | D35: =IFERROR(SUMIFS('🏃 Sprints'!J:J,'🏃 Sprints'!A:A,$A35,'🏃 Sprints'!B:B,$B35),0) -> 238 | E35: =C35/D35 -> 0.42857143 | F35: =IF(E35="","",IF(E35<=0.2,"🟢 Green",IF(E35<=0.3,"🟡 Yellow","🔴 Red"))) -> 🔴 Red | G35: The rework % increase due to Team 1 uncovering App Packet and Policy Packet form related defects | H35: Coding/design errors - Solution lead of team 1 agreed to increase unit testing coverage
A36: Q2 Sprint 3 | B36: May | C36: =IFERROR(SUMIFS('🏃 Sprints'!H:H,'🏃 Sprints'!A:A,$A36,'🏃 Sprints'!B:B,$B36),0) -> 61 | D36: =IFERROR(SUMIFS('🏃 Sprints'!J:J,'🏃 Sprints'!A:A,$A36,'🏃 Sprints'!B:B,$B36),0) -> 300 | E36: =C36/D36 -> 0.20333333 | F36: =IF(E36="","",IF(E36<=0.2,"🟢 Green",IF(E36<=0.3,"🟡 Yellow","🔴 Red"))) -> 🟡 Yellow | G36: The rework % came down as more story points completed in this sprint
A37: Q2 Sprint 4 | B37: May | C37: =IFERROR(SUMIFS('🏃 Sprints'!H:H,'🏃 Sprints'!A:A,$A37,'🏃 Sprints'!B:B,$B37),0) -> 90 | D37: =IFERROR(SUMIFS('🏃 Sprints'!J:J,'🏃 Sprints'!A:A,$A37,'🏃 Sprints'!B:B,$B37),0) -> 257 | E37: =C37/D37 -> 0.35019455 | F37: =IF(E37="","",IF(E37<=0.2,"🟢 Green",IF(E37<=0.3,"🟡 Yellow","🔴 Red"))) -> 🔴 Red | G37: Team 1 primarily worked on Release 1.1 and 1.2 activities ( thus increasing the rework percentage) Team 2 also worked on more defects compared to previous sprint leading up to Final Expense Pilot release. Team 4 worked on more defects as well in this sprint.
A38: Q2 Sprint 5 | B38: June | C38: =IFERROR(SUMIFS('🏃 Sprints'!H:H,'🏃 Sprints'!A:A,$A38,'🏃 Sprints'!B:B,$B38),0) -> 104 | D38: =IFERROR(SUMIFS('🏃 Sprints'!J:J,'🏃 Sprints'!A:A,$A38,'🏃 Sprints'!B:B,$B38),0) -> 317 | E38: =C38/D38 -> 0.32807571 | F38: =IF(E38="","",IF(E38<=0.2,"🟢 Green",IF(E38<=0.3,"🟡 Yellow","🔴 Red"))) -> 🔴 Red | G38: Team 1 primarily worked on bugs as part of Release activities ( thus increasing the rework percentage) Team 2 also worked on more defects compared to previous sprint leading up to Final Expense Pilot release.
A39: Q2 Sprint 6 | B39: June | C39: =IFERROR(SUMIFS('🏃 Sprints'!H:H,'🏃 Sprints'!A:A,$A39,'🏃 Sprints'!B:B,$B39),0) -> 73 | D39: =IFERROR(SUMIFS('🏃 Sprints'!J:J,'🏃 Sprints'!A:A,$A39,'🏃 Sprints'!B:B,$B39),0) -> 202 | E39: =C39/D39 -> 0.36138614 | F39: =IF(E39="","",IF(E39<=0.2,"🟢 Green",IF(E39<=0.3,"🟡 Yellow","🔴 Red"))) -> 🔴 Red | G39: Team 1 primarily worked on bugs as part of Release activities ( thus increasing the rework percentage) Team 2 also worked on more defects compared to previous sprint leading up to Final Expense Pilot release.
E40: =IF(C40+D40=0,"",C40+D40) | F40: =IFERROR(IF(E40="","",E40/B40),"") | G40: =IF(F40="","",IF(F40<=0.2,"🟢 Green",IF(F40<=0.3,"🟡 Yellow","🔴 Red")))
A44: SECTION D — First Time Pass Rate- >=95% : Green, >85% : Yellow, <=85% Red
A45: First Time Pass Rate = Total Stories with defects/ Total Completed Story Points × 100
A46: Sprint ID | B46: Month | C46: Total Stories W/O defects | D46: Total Stories Delivered | E46: First Time Pass % | F46: Status | G46: Notes
A47: Sprint 1 | B47: January | C47: =IFERROR(SUMIFS(FTPR!H:H,FTPR!A:A,$A47,FTPR!E:E,$B47),0) -> 0 | D47: =IFERROR(SUMIFS(FTPR!F:F,FTPR!A:A,$A47,FTPR!E:E,$B47),0) -> 0 | E47: =C47/D47 -> #DIV/0! | F47: =IF(E47="","",IF(E47>=0.95,"🟢 Green",IF(E47<0.85,"🟡 Yellow","🔴 Red"))) -> #DIV/0!
A48: Sprint 2 | B48: February | C48: =IFERROR(SUMIFS(FTPR!H:H,FTPR!A:A,$A48,FTPR!E:E,$B48),0) -> 0 | D48: =IFERROR(SUMIFS(FTPR!F:F,FTPR!A:A,$A48,FTPR!E:E,$B48),0) -> 0 | E48: =C48/D48 -> #DIV/0! | F48: =IF(E48="","",IF(E48>=0.95,"🟢 Green",IF(E48<0.85,"🟡 Yellow","🔴 Red"))) -> #DIV/0!
A49: Sprint 3 | B49: February | C49: =IFERROR(SUMIFS(FTPR!H:H,FTPR!A:A,$A49,FTPR!E:E,$B49),0) -> 0 | D49: =IFERROR(SUMIFS(FTPR!F:F,FTPR!A:A,$A49,FTPR!E:E,$B49),0) -> 0 | E49: =C49/D49 -> #DIV/0! | F49: =IF(E49="","",IF(E49>=0.95,"🟢 Green",IF(E49<0.85,"🟡 Yellow","🔴 Red"))) -> #DIV/0!
A50: Sprint 4 | B50: March | C50: =IFERROR(SUMIFS(FTPR!H:H,FTPR!A:A,$A50,FTPR!E:E,$B50),0) -> 0 | D50: =IFERROR(SUMIFS(FTPR!F:F,FTPR!A:A,$A50,FTPR!E:E,$B50),0) -> 0 | E50: =C50/D50 -> #DIV/0! | F50: =IF(E50="","",IF(E50>=0.95,"🟢 Green",IF(E50<0.85,"🟡 Yellow","🔴 Red"))) -> #DIV/0!
A51: Sprint 5 | B51: March | C51: =IFERROR(SUMIFS(FTPR!H:H,FTPR!A:A,$A51,FTPR!E:E,$B51),0) -> 84 | D51: =IFERROR(SUMIFS(FTPR!F:F,FTPR!A:A,$A51,FTPR!E:E,$B51),0) -> 98 | E51: =C51/D51 -> 0.85714286 | F51: =IF(E51="","",IF(E51>=0.95,"🟢 Green",IF(E51<0.85,"🔴 Red","🟡 Yellow"))) -> 🟡 Yellow
A52: Sprint 6 | B52: March | C52: =IFERROR(SUMIFS(FTPR!H:H,FTPR!A:A,$A52,FTPR!E:E,$B52),0) -> 67 | D52: =IFERROR(SUMIFS(FTPR!F:F,FTPR!A:A,$A52,FTPR!E:E,$B52),0) -> 77 | E52: =C52/D52 -> 0.87012987 | F52: =IF(E52="","",IF(E52>=0.95,"🟢 Green",IF(E52<0.85,"🔴 Red","🟡 Yellow"))) -> 🟡 Yellow
A53: Q2 Sprint 1 | B53: April | C53: =IFERROR(SUMIFS(FTPR!H:H,FTPR!A:A,$A53,FTPR!E:E,$B53),0) -> 89 | D53: =IFERROR(SUMIFS(FTPR!F:F,FTPR!A:A,$A53,FTPR!E:E,$B53),0) -> 119 | E53: =C53/D53 -> 0.74789916 | F53: =IF(E53="","",IF(E53>=0.95,"🟢 Green",IF(E53<0.85,"🔴 Red","🟡 Yellow"))) -> 🔴 Red | G53: Team 1 has only 51% FTPR in this sprint
A54: Q2 Sprint 2 | B54: April | C54: =IFERROR(SUMIFS(FTPR!H:H,FTPR!A:A,$A54,FTPR!E:E,$B54),0) -> 66 | D54: =IFERROR(SUMIFS(FTPR!F:F,FTPR!A:A,$A54,FTPR!E:E,$B54),0) -> 73 | E54: =C54/D54 -> 0.90410959 | F54: =IF(E54="","",IF(E54>=0.95,"🟢 Green",IF(E54<0.85,"🔴 Red","🟡 Yellow"))) -> 🟡 Yellow | G54: Team 1 has 75% FTPR. Improvement due to 5 why analysis and mitigation actions, i.e. Additional Code Review and Unit testing Coverage. Team 2,3 & 4 also shown better results
A55: Q2 Sprint 3 | B55: May | C55: =IFERROR(SUMIFS(FTPR!H:H,FTPR!A:A,$A55,FTPR!E:E,$B55),0) -> 83 | D55: =IFERROR(SUMIFS(FTPR!F:F,FTPR!A:A,$A55,FTPR!E:E,$B55),0) -> 107 | E55: =C55/D55 -> 0.77570093 | F55: =IF(E55="","",IF(E55>=0.95,"🟢 Green",IF(E55<0.85,"🔴 Red","🟡 Yellow"))) -> 🔴 Red | G55: Team 2 FTPR was 65% in this sprint, other teams were consistent. 5 Why results awaited.
A56: Q2 Sprint 4 | B56: May | C56: =IFERROR(SUMIFS(FTPR!H:H,FTPR!A:A,$A56,FTPR!E:E,$B56),0) -> 64 | D56: =IFERROR(SUMIFS(FTPR!F:F,FTPR!A:A,$A56,FTPR!E:E,$B56),0) -> 73 | E56: =C56/D56 -> 0.87671233 | F56: =IF(E56="","",IF(E56>=0.95,"🟢 Green",IF(E56<0.85,"🔴 Red","🟡 Yellow"))) -> 🟡 Yellow | G56: FTPR improved to 79% for team 2, other teams were consistent
A57: Q2 Sprint 5 | B57: June | C57: =IFERROR(SUMIFS(FTPR!H:H,FTPR!A:A,$A57,FTPR!E:E,$B57),0) -> 81 | D57: =IFERROR(SUMIFS(FTPR!F:F,FTPR!A:A,$A57,FTPR!E:E,$B57),0) -> 102 | E57: =C57/D57 -> 0.79411765 | F57: =IF(E57="","",IF(E57>=0.95,"🟢 Green",IF(E57<0.85,"🔴 Red","🟡 Yellow"))) -> 🔴 Red | G57: FTPR was 66% for team 2 and 68% for team 1, other teams were consistent | H57: Enforce 5-Why ( Pending For team 1 & 2 from SP2)
A58: Q2 Sprint 6 | B58: June | C58: =IFERROR(SUMIFS(FTPR!H:H,FTPR!A:A,$A58,FTPR!E:E,$B58),0) -> 51 | D58: =IFERROR(SUMIFS(FTPR!F:F,FTPR!A:A,$A58,FTPR!E:E,$B58),0) -> 60 | E58: =C58/D58 -> 0.85 | F58: =IF(E58="","",IF(E58>=0.95,"🟢 Green",IF(E58<0.85,"🔴 Red","🟡 Yellow"))) -> 🟡 Yellow | G58: Team 4 didnt have any defects in this sprint and Team 3 has improved
A60: SECTION E — In Sprint Automation
A61: Team | B61: SprintId | C61: TOTAL STORY CARDS | D61: Automatable Cards | E61: Test Cards Actually Automated | F61: Manually executed Cards | G61: %Automated | H61: Comments | I61: Total Bugs
A62: Team 1 | B62: SP1 | C62: 48 | D62: 17(7(VAM)+10(Innova)) | E62: 0 | F62: 71 | G62: 0 | H62: Lack of Bandwidth due to pilot testing, 50% more Sprint cards delivered compared to average velocity | I62: 23
A63: Team 2 | B63: SP1 | C63: 16 | D63: 7 | E63: 5 | F63: 12 | G63: 0.71 | H63: Able to achieve 71% insprint Automation | I63: 1
A64: Team 3 | B64: SP1 | C64: 17 | D64: 2 | E64: 1 | F64: 24 | G64: 0.5 | H64: 50% achieved.As discussed with Karthik, release 1.1 related cards were automated | I64: 7
A65: Team 1 | B65: SP2 | C65: 16 | D65: 7(2(VAM)+5(Innova)) | E65: 2 | F65: 87 | G65: 0.2857 | H65: 28.57% achieved. As discussed with Karthik, only release 1.1 related cards were automated | I65: 73
A66: Team 2 | B66: SP2 | C66: 57 | D66: 6 | E66: 0 | F66: 60 | G66: 0 | H66: Team had about 90% more story cards allocated than average in this sprint | I66: 3
A67: Team 3 | B67: SP2 | C67: 8 | D67: 0 | E67: 0 | F67: 11 | G67: NA | I67: 3
A68: Team-1 | B68: SP3 | C68: 20 | D68: 0 | E68: 0 | F68: 28 | G68: NA | I68: 28
A69: Team 2 | B69: SP3 | C69: 52 | D69: 0 | E69: 0 | F69: 75 | G69: NA | I69: 23
A70: Team 3 | B70: SP3 | C70: 19 | D70: 2 | E70: 0 | F70: 21 | G70: 0 | H70: Lack of Bandwidth due to pilot testing , cross product testing,and sprint work | I70: 3
A71: Team-1 | B71: SP4 | C71: 29 | D71: 0 | E71: 0 | F71: 82 | G71: NA | I71: 53
A72: Team 2 | B72: SP4 | C72: 30 | D72: 0 | E72: 0 | F72: 49 | G72: NA | I72: 19
A73: Team 3 | B73: SP4 | C73: 4 | D73: 2 | E73: 0 | F73: 5 | G73: 0 | H73: Lack of Bandwidth due to pilot testing , cross product testing,and sprint work | I73: 1
A74: Team-1 | B74: SP5 | C74: 29 | D74: 14 | E74: 10 | F74: 4 | G74: 0.7143
A75: Team 2 | B75: SP5 | C75: 4 | D75: 1 | E75: 0 | F75: 1 | G75: 0 | H75: Team was occupied with FE Release activities
A76: Team 3 | B76: SP5 | C76: 23 | D76: 4 | E76: 0 | F76: 4 | G76: 0 | H76: Team was occupied with 1.3 and Enterprise Release activities
A77: Team-1 | B77: SP6 | C77: 17 | D77: 9 | E77: 2 | F77: 7 | G77: 0.2222
A78: Team 2 | B78: SP6 | C78: 8 | D78: 0 | E78: 0 | F78: 8 | G78: 0 | H78: Worked on regression for FE
A79: Team 3 | B79: SP6 | C79: 8 | D79: 1 | E79: 0 | F79: 8 | G79: 0 | H79: Team was occupied with 1.4 and Enterprise Release activities

Sheet 🏃 Sprints
A1: SPRINT DATA INPUT — Per Sprint
A2: 1. Commitment Reliability - Delivery Predictability, Overcommitment vs execution blockers 2. Cycle Time (Median) - How fast value is delivered and Team efficiency
A3: SECTION A — Commitment Reliability (<75% - Red; >=75 to <85% - Yellow; >=85% - Green)
A4: Sprint ID | B4: Month | C4: Stories Planned | D4: Stories Defects Planned | E4: Standalone Bugs Planned | F4: Stories Completed | G4: Story Defects Completed | H4: Standalone Bugs Completed | I4: Total Planned (Exclude Story defects) | J4: Total Completed (Exclude Story defects) | K4: Baseline Velocity | L4: Completion % | M4: CR Status | N4: VM Completed Stories | O4: VM Standalone Bugs Completed | P4: Notes
A5: Sprint 1 | B5: January | C5: =SUMIFS('Team Sprints Input'!F:F,'Team Sprints Input'!$A:$A,$A5) -> 250 | D5: =SUMIFS('Team Sprints Input'!G:G,'Team Sprints Input'!$A:$A,$A5) -> 24 | E5: =SUMIFS('Team Sprints Input'!H:H,'Team Sprints Input'!$A:$A,$A5) -> 10 | F5: =SUMIFS('Team Sprints Input'!I:I,'Team Sprints Input'!$A:$A,$A5) -> 112 | G5: =SUMIFS('Team Sprints Input'!J:J,'Team Sprints Input'!$A:$A,$A5) -> 8 | H5: =SUMIFS('Team Sprints Input'!K:K,'Team Sprints Input'!$A:$A,$A5) -> 4 | I5: =C5+E5 -> 260 | J5: =F5+H5 -> 116 | K5: =SUMIFS('Team Sprints Input'!N:N, 'Team Sprints Input'!A:A, A5, 'Team Sprints Input'!E:E, B5) -> 116 | L5: =IFERROR(J5/K5,"") -> 1 | M5: =IF(L5="","",IF(L5>=0.85,"🟢 Green",IF(L5>=0.75,"🟡 Yellow","🔴 Red"))) -> 🟢 Green | N5: =SUMIFS('VAM Team Sprint-CostperSprint'!I:I,'VAM Team Sprint-CostperSprint'!$A:$A,$A5) -> 84 | O5: =SUMIFS('VAM Team Sprint-CostperSprint'!H:H,'VAM Team Sprint-CostperSprint'!$A:$A,$A5) -> 4
A6: Sprint 2 | B6: February | C6: =SUMIFS('Team Sprints Input'!F:F,'Team Sprints Input'!$A:$A,$A6) -> 588 | D6: =SUMIFS('Team Sprints Input'!G:G,'Team Sprints Input'!$A:$A,$A6) -> 40 | E6: =SUMIFS('Team Sprints Input'!H:H,'Team Sprints Input'!$A:$A,$A6) -> 64 | F6: =SUMIFS('Team Sprints Input'!I:I,'Team Sprints Input'!$A:$A,$A6) -> 370 | G6: =SUMIFS('Team Sprints Input'!J:J,'Team Sprints Input'!$A:$A,$A6) -> 41 | H6: =SUMIFS('Team Sprints Input'!K:K,'Team Sprints Input'!$A:$A,$A6) -> 34 | I6: =C6+E6 -> 652 | J6: =F6+H6 -> 404 | K6: =SUMIFS('Team Sprints Input'!N:N, 'Team Sprints Input'!A:A, A6, 'Team Sprints Input'!E:E, B6) -> 316 | L6: =IFERROR(J6/K6,"") -> 1.278481 | M6: =IF(L6="","",IF(L6>=0.85,"🟢 Green",IF(L6>=0.75,"🟡 Yellow","🔴 Red"))) -> 🟢 Green | N6: =SUMIFS('VAM Team Sprint-CostperSprint'!I:I,'VAM Team Sprint-CostperSprint'!$A:$A,$A6) -> 178 | O6: =SUMIFS('VAM Team Sprint-CostperSprint'!H:H,'VAM Team Sprint-CostperSprint'!$A:$A,$A6) -> 22
A7: Sprint 3 | B7: February | C7: =SUMIFS('Team Sprints Input'!F:F,'Team Sprints Input'!$A:$A,$A7) -> 439 | D7: =SUMIFS('Team Sprints Input'!G:G,'Team Sprints Input'!$A:$A,$A7) -> 31 | E7: =SUMIFS('Team Sprints Input'!H:H,'Team Sprints Input'!$A:$A,$A7) -> 144 | F7: =SUMIFS('Team Sprints Input'!I:I,'Team Sprints Input'!$A:$A,$A7) -> 140 | G7: =SUMIFS('Team Sprints Input'!J:J,'Team Sprints Input'!$A:$A,$A7) -> 10 | H7: =SUMIFS('Team Sprints Input'!K:K,'Team Sprints Input'!$A:$A,$A7) -> 75 | I7: =C7+E7 -> 583 | J7: =F7+H7 -> 215 | K7: =SUMIFS('Team Sprints Input'!N:N, 'Team Sprints Input'!A:A, A7, 'Team Sprints Input'!E:E, B7) -> 316 | L7: =IFERROR(J7/K7,"") -> 0.68037975 | M7: =IF(L7="","",IF(L7>=0.85,"🟢 Green",IF(L7>=0.75,"🟡 Yellow","🔴 Red"))) -> 🔴 Red | N7: =SUMIFS('VAM Team Sprint-CostperSprint'!I:I,'VAM Team Sprint-CostperSprint'!$A:$A,$A7) -> 147 | O7: =SUMIFS('VAM Team Sprint-CostperSprint'!H:H,'VAM Team Sprint-CostperSprint'!$A:$A,$A7) -> 66
A8: Sprint 4 | B8: March | C8: =SUMIFS('Team Sprints Input'!F:F,'Team Sprints Input'!$A:$A,$A8) -> 605 | D8: =SUMIFS('Team Sprints Input'!G:G,'Team Sprints Input'!$A:$A,$A8) -> 17 | E8: =SUMIFS('Team Sprints Input'!H:H,'Team Sprints Input'!$A:$A,$A8) -> 158 | F8: =SUMIFS('Team Sprints Input'!I:I,'Team Sprints Input'!$A:$A,$A8) -> 312 | G8: =SUMIFS('Team Sprints Input'!J:J,'Team Sprints Input'!$A:$A,$A8) -> 43 | H8: =SUMIFS('Team Sprints Input'!K:K,'Team Sprints Input'!$A:$A,$A8) -> 127 | I8: =C8+E8 -> 763 | J8: =F8+H8 -> 439 | K8: =SUMIFS('Team Sprints Input'!N:N, 'Team Sprints Input'!A:A, A8, 'Team Sprints Input'!E:E, B8) -> 316 | L8: =IFERROR(J8/K8,"") -> 1.3892405 | M8: =IF(L8="","",IF(L8>=0.85,"🟢 Green",IF(L8>=0.75,"🟡 Yellow","🔴 Red"))) -> 🟢 Green | N8: =SUMIFS('VAM Team Sprint-CostperSprint'!I:I,'VAM Team Sprint-CostperSprint'!$A:$A,$A8) -> 323 | O8: =SUMIFS('VAM Team Sprint-CostperSprint'!H:H,'VAM Team Sprint-CostperSprint'!$A:$A,$A8) -> 108
A9: Sprint 5 | B9: March | C9: =SUMIFS('Team Sprints Input'!F:F,'Team Sprints Input'!$A:$A,$A9) -> 628 | D9: =SUMIFS('Team Sprints Input'!G:G,'Team Sprints Input'!$A:$A,$A9) -> 13 | E9: =SUMIFS('Team Sprints Input'!H:H,'Team Sprints Input'!$A:$A,$A9) -> 92 | F9: =SUMIFS('Team Sprints Input'!I:I,'Team Sprints Input'!$A:$A,$A9) -> 291 | G9: =SUMIFS('Team Sprints Input'!J:J,'Team Sprints Input'!$A:$A,$A9) -> 34 | H9: =SUMIFS('Team Sprints Input'!K:K,'Team Sprints Input'!$A:$A,$A9) -> 60 | I9: =C9+D9+E9 -> 733 | J9: =F9+H9 -> 351 | K9: =SUMIFS('Team Sprints Input'!N:N, 'Team Sprints Input'!A:A, A9, 'Team Sprints Input'!E:E, B9) -> 316 | L9: =IFERROR(J9/K9,"") -> 1.1107595 | M9: =IF(L9="","",IF(L9>=0.85,"🟢 Green",IF(L9>=0.75,"🟡 Yellow","🔴 Red"))) -> 🟢 Green | N9: =SUMIFS('VAM Team Sprint-CostperSprint'!I:I,'VAM Team Sprint-CostperSprint'!$A:$A,$A9) -> 164 | O9: =SUMIFS('VAM Team Sprint-CostperSprint'!H:H,'VAM Team Sprint-CostperSprint'!$A:$A,$A9) -> 37
A10: Sprint 6 | B10: March | C10: =SUMIFS('Team Sprints Input'!F:F,'Team Sprints Input'!$A:$A,$A10) -> 520 | D10: =SUMIFS('Team Sprints Input'!G:G,'Team Sprints Input'!$A:$A,$A10) -> 26 | E10: =SUMIFS('Team Sprints Input'!H:H,'Team Sprints Input'!$A:$A,$A10) -> 64 | F10: =SUMIFS('Team Sprints Input'!I:I,'Team Sprints Input'!$A:$A,$A10) -> 172 | G10: =SUMIFS('Team Sprints Input'!J:J,'Team Sprints Input'!$A:$A,$A10) -> 23 | H10: =SUMIFS('Team Sprints Input'!K:K,'Team Sprints Input'!$A:$A,$A10) -> 39 | I10: =C10+D10+E10 -> 610 | J10: =F10+H10 -> 211 | K10: =SUMIFS('Team Sprints Input'!N:N, 'Team Sprints Input'!A:A, A10, 'Team Sprints Input'!E:E, B10) -> 316 | L10: =IFERROR(J10/K10,"") -> 0.66772152 | M10: =IF(L10="","",IF(L10>=0.85,"🟢 Green",IF(L10>=0.75,"🟡 Yellow","🔴 Red"))) -> 🔴 Red | N10: =SUMIFS('VAM Team Sprint-CostperSprint'!I:I,'VAM Team Sprint-CostperSprint'!$A:$A,$A10) -> 113 | O10: =SUMIFS('VAM Team Sprint-CostperSprint'!H:H,'VAM Team Sprint-CostperSprint'!$A:$A,$A10) -> 20
A11: Q2 Sprint 1 | B11: April | C11: =SUMIFS('Team Sprints Input'!F:F,'Team Sprints Input'!$A:$A,$A11) -> 634 | D11: =SUMIFS('Team Sprints Input'!G:G,'Team Sprints Input'!$A:$A,$A11) -> 12 | E11: =SUMIFS('Team Sprints Input'!H:H,'Team Sprints Input'!$A:$A,$A11) -> 59 | F11: =SUMIFS('Team Sprints Input'!I:I,'Team Sprints Input'!$A:$A,$A11) -> 270 | G11: =SUMIFS('Team Sprints Input'!J:J,'Team Sprints Input'!$A:$A,$A11) -> 57 | H11: =SUMIFS('Team Sprints Input'!K:K,'Team Sprints Input'!$A:$A,$A11) -> 37 | I11: =C11+D11+E11 -> 705 | J11: =F11+H11 -> 307 | K11: =SUMIFS('Team Sprints Input'!N:N, 'Team Sprints Input'!A:A, A11, 'Team Sprints Input'!E:E, B11) -> 316 | L11: =IFERROR(J11/K11,"") -> 0.97151899 | M11: =IF(L11="","",IF(L11>=0.85,"🟢 Green",IF(L11>=0.75,"🟡 Yellow","🔴 Red"))) -> 🟢 Green | N11: =SUMIFS('VAM Team Sprint-CostperSprint'!I:I,'VAM Team Sprint-CostperSprint'!$A:$A,$A11) -> 220 | O11: =SUMIFS('VAM Team Sprint-CostperSprint'!H:H,'VAM Team Sprint-CostperSprint'!$A:$A,$A11) -> 22
A12: Q2 Sprint 2 | B12: April | C12: =SUMIFS('Team Sprints Input'!F:F,'Team Sprints Input'!$A:$A,$A12) -> 648 | D12: =SUMIFS('Team Sprints Input'!G:G,'Team Sprints Input'!$A:$A,$A12) -> 13 | E12: =SUMIFS('Team Sprints Input'!H:H,'Team Sprints Input'!$A:$A,$A12) -> 145 | F12: =SUMIFS('Team Sprints Input'!I:I,'Team Sprints Input'!$A:$A,$A12) -> 136 | G12: =SUMIFS('Team Sprints Input'!J:J,'Team Sprints Input'!$A:$A,$A12) -> 11 | H12: =SUMIFS('Team Sprints Input'!K:K,'Team Sprints Input'!$A:$A,$A12) -> 102 | I12: =C12+D12+E12 -> 806 | J12: =F12+H12 -> 238 | K12: =SUMIFS('Team Sprints Input'!N:N, 'Team Sprints Input'!A:A, A12, 'Team Sprints Input'!E:E, B12) -> 316 | L12: =IFERROR(J12/K12,"") -> 0.75316456 | M12: =IF(L12="","",IF(L12>=0.85,"🟢 Green",IF(L12>=0.75,"🟡 Yellow","🔴 Red"))) -> 🟡 Yellow | N12: =SUMIFS('VAM Team Sprint-CostperSprint'!I:I,'VAM Team Sprint-CostperSprint'!$A:$A,$A12) -> 141 | O12: =SUMIFS('VAM Team Sprint-CostperSprint'!H:H,'VAM Team Sprint-CostperSprint'!$A:$A,$A12) -> 57
A13: Q2 Sprint 3 | B13: May | C13: =SUMIFS('Team Sprints Input'!F:F,'Team Sprints Input'!$A:$A,$A13) -> 586 | D13: =SUMIFS('Team Sprints Input'!G:G,'Team Sprints Input'!$A:$A,$A13) -> 5 | E13: =SUMIFS('Team Sprints Input'!H:H,'Team Sprints Input'!$A:$A,$A13) -> 108 | F13: =SUMIFS('Team Sprints Input'!I:I,'Team Sprints Input'!$A:$A,$A13) -> 207 | G13: =SUMIFS('Team Sprints Input'!J:J,'Team Sprints Input'!$A:$A,$A13) -> 32 | H13: =SUMIFS('Team Sprints Input'!K:K,'Team Sprints Input'!$A:$A,$A13) -> 61 | I13: =C13+D13+E13 -> 699 | J13: =F13+G13+H13 -> 300 | K13: =SUMIFS('Team Sprints Input'!N:N, 'Team Sprints Input'!A:A, A13, 'Team Sprints Input'!E:E, B13) -> 140 | L13: =IFERROR(J13/I13,"") -> 0.42918455 | M13: =IF(L13="","",IF(L13>=0.85,"🟢 Green",IF(L13>=0.75,"🟡 Yellow","🔴 Red"))) -> 🔴 Red | N13: =SUMIFS('VAM Team Sprint-CostperSprint'!I:I,'VAM Team Sprint-CostperSprint'!$A:$A,$A13) -> 169 | O13: =SUMIFS('VAM Team Sprint-CostperSprint'!H:H,'VAM Team Sprint-CostperSprint'!$A:$A,$A13) -> 41
A14: Q2 Sprint 4 | B14: May | C14: =SUMIFS('Team Sprints Input'!F:F,'Team Sprints Input'!$A:$A,$A14) -> 485 | D14: =SUMIFS('Team Sprints Input'!G:G,'Team Sprints Input'!$A:$A,$A14) -> 11 | E14: =SUMIFS('Team Sprints Input'!H:H,'Team Sprints Input'!$A:$A,$A14) -> 128 | F14: =SUMIFS('Team Sprints Input'!I:I,'Team Sprints Input'!$A:$A,$A14) -> 147 | G14: =SUMIFS('Team Sprints Input'!J:J,'Team Sprints Input'!$A:$A,$A14) -> 20 | H14: =SUMIFS('Team Sprints Input'!K:K,'Team Sprints Input'!$A:$A,$A14) -> 90 | I14: =C14+D14+E14 -> 624 | J14: =F14+G14+H14 -> 257 | K14: =SUMIFS('Team Sprints Input'!N:N, 'Team Sprints Input'!A:A, A14, 'Team Sprints Input'!E:E, B14) -> 140 | L14: =IFERROR(J14/I14,"") -> 0.41185897 | M14: =IF(L14="","",IF(L14>=0.85,"🟢 Green",IF(L14>=0.75,"🟡 Yellow","🔴 Red"))) -> 🔴 Red | N14: =SUMIFS('VAM Team Sprint-CostperSprint'!I:I,'VAM Team Sprint-CostperSprint'!$A:$A,$A14) -> 162 | O14: =SUMIFS('VAM Team Sprint-CostperSprint'!H:H,'VAM Team Sprint-CostperSprint'!$A:$A,$A14) -> 48
A15: Q2 Sprint 5 | B15: June | C15: =SUMIFS('Team Sprints Input'!F:F,'Team Sprints Input'!$A:$A,$A15) -> 397 | D15: =SUMIFS('Team Sprints Input'!G:G,'Team Sprints Input'!$A:$A,$A15) -> 9 | E15: =SUMIFS('Team Sprints Input'!H:H,'Team Sprints Input'!$A:$A,$A15) -> 133 | F15: =SUMIFS('Team Sprints Input'!I:I,'Team Sprints Input'!$A:$A,$A15) -> 185 | G15: =SUMIFS('Team Sprints Input'!J:J,'Team Sprints Input'!$A:$A,$A15) -> 28 | H15: =SUMIFS('Team Sprints Input'!K:K,'Team Sprints Input'!$A:$A,$A15) -> 104 | I15: =C15+D15+E15 -> 539 | J15: =F15+G15+H15 -> 317 | K15: =SUMIFS('Team Sprints Input'!N:N, 'Team Sprints Input'!A:A, A15, 'Team Sprints Input'!E:E, B15) -> 140 | L15: =IFERROR(J15/I15,"") -> 0.58812616 | M15: =IF(L15="","",IF(L15>=0.85,"🟢 Green",IF(L15>=0.75,"🟡 Yellow","🔴 Red"))) -> 🔴 Red | N15: =SUMIFS('VAM Team Sprint-CostperSprint'!I:I,'VAM Team Sprint-CostperSprint'!$A:$A,$A15) -> 215 | O15: =SUMIFS('VAM Team Sprint-CostperSprint'!H:H,'VAM Team Sprint-CostperSprint'!$A:$A,$A15) -> 83
A16: Q2 Sprint 6 | B16: June | C16: =SUMIFS('Team Sprints Input'!F:F,'Team Sprints Input'!$A:$A,$A16) -> 401 | D16: =SUMIFS('Team Sprints Input'!G:G,'Team Sprints Input'!$A:$A,$A16) -> 1 | E16: =SUMIFS('Team Sprints Input'!H:H,'Team Sprints Input'!$A:$A,$A16) -> 144 | F16: =SUMIFS('Team Sprints Input'!I:I,'Team Sprints Input'!$A:$A,$A16) -> 122 | G16: =SUMIFS('Team Sprints Input'!J:J,'Team Sprints Input'!$A:$A,$A16) -> 7 | H16: =SUMIFS('Team Sprints Input'!K:K,'Team Sprints Input'!$A:$A,$A16) -> 73 | I16: =C16+D16+E16 -> 546 | J16: =F16+G16+H16 -> 202 | K16: =SUMIFS('Team Sprints Input'!N:N, 'Team Sprints Input'!A:A, A16, 'Team Sprints Input'!E:E, B16) -> 140 | L16: =IFERROR(J16/I16,"") -> 0.36996337 | M16: =IF(L16="","",IF(L16>=0.85,"🟢 Green",IF(L16>=0.75,"🟡 Yellow","🔴 Red"))) -> 🔴 Red | N16: =SUMIFS('VAM Team Sprint-CostperSprint'!I:I,'VAM Team Sprint-CostperSprint'!$A:$A,$A16) -> 135 | O16: =SUMIFS('VAM Team Sprint-CostperSprint'!H:H,'VAM Team Sprint-CostperSprint'!$A:$A,$A16) -> 50
A17: Sprint 7 | B17: August | J17: =IF(D17+E17+F17=0,"",D17+E17+F17) | L17: =IF(G17+H17+I17=0,"",G17+H17+I17) | M17: =IFERROR(L17/J17,"") | P17: =IF(M17="","",IF(M17>=0.85,"🟢 Green",IF(M17>=0.75,"🟡 Yellow","🔴 Red")))
A19: MONTHLY ROLLUP — Commitment Reliability (Stable, Improving and Declining) | G19: MONTHLY ROLLUP — Commitment Reliability (Stable, Improving and Declining)
A20: Month | B20: Sprints in Month | C20: Avg Completion % | D20: Monthly CR Status | E20: 3-Sprint Trend | G20: Month | H20: Sprints in Month | I20: Avg Completion % | J20: Monthly CR Status | K20: 3-Sprint Trend
A21: January | B21: =COUNTIF(B5:B17,A21) -> 1 | C21: =IFERROR(AVERAGEIF($B$5:$B$17,A21,$L$5:$L$17),"") -> 1 | D21: =IF(C21="","",IF(C21>=0.85,"🟢 Green",IF(C21>=0.75,"🟡 Yellow","🔴 Red"))) -> 🟢 Green | E21: =IF(COUNTA(C21:C21)<3,"(need 3mo)",IF(AVERAGE(C21:C21)>=0.85,"↑ Improving",IF(AVERAGE(C21:C21)>=0.75,"→ Stable","↓ Declining"))) -> (need 3mo) | G21: June | H21: =COUNTIF(B5:B20,G21) -> 2 | I21: =IFERROR(AVERAGEIF($B$5:$B$17,G21,$L$5:$L$17),"") -> 0.47904476 | J21: =IF(I21="","",IF(I21>=0.85,"🟢 Green",IF(I21>=0.75,"🟡 Yellow","🔴 Red"))) -> 🔴 Red | K21: =IF(COUNTA(C24:C25,I21)<3,"(need 3mo)",IF(AVERAGE(C24:C25,I21)>=0.85,"↑ Improving",IF(AVERAGE(C24:C25,I21)>=0.75,"→ Stable","↓ Declining"))) -> ↓ Declining
A22: February | B22: =COUNTIF(B6:B18,A22) -> 2 | C22: =IFERROR(AVERAGEIF($B$5:$B$17,A22,$L$5:$L$17),"") -> 0.97943038 | D22: =IF(C22="","",IF(C22>=0.85,"🟢 Green",IF(C22>=0.75,"🟡 Yellow","🔴 Red"))) -> 🟢 Green | E22: =IF(COUNTA(C21:C22)<3,"(need 3mo)",IF(AVERAGE(C21:C22)>=0.85,"↑ Improving",IF(AVERAGE(C21:C22)>=0.75,"→ Stable","↓ Declining"))) -> (need 3mo)
A23: March | B23: =COUNTIF(B7:B19,A23) -> 3 | C23: =IFERROR(AVERAGEIF($B$5:$B$17,A23,$L$5:$L$17),"") -> 1.0559072 | D23: =IF(C23="","",IF(C23>=0.85,"🟢 Green",IF(C23>=0.75,"🟡 Yellow","🔴 Red"))) -> 🟢 Green | E23: =IF(COUNTA(C21:C23)<3,"(need 3mo)",IF(AVERAGE(C21:C23)>=0.85,"↑ Improving",IF(AVERAGE(C21:C23)>=0.75,"→ Stable","↓ Declining"))) -> ↑ Improving
A24: April | B24: =COUNTIF(B8:B20,A24) -> 2 | C24: =IFERROR(AVERAGEIF($B$5:$B$17,A24,$L$5:$L$17),"") -> 0.86234177 | D24: =IF(C24="","",IF(C24>=0.85,"🟢 Green",IF(C24>=0.75,"🟡 Yellow","🔴 Red"))) -> 🟢 Green | E24: =IF(COUNTA(C22:C24)<3,"(need 3mo)",IF(AVERAGE(C22:C24)>=0.85,"↑ Improving",IF(AVERAGE(C22:C24)>=0.75,"→ Stable","↓ Declining"))) -> ↑ Improving
A25: May | B25: =COUNTIF(B9:B21,A25) -> 2 | C25: =IFERROR(AVERAGEIF($B$5:$B$17,A25,$L$5:$L$17),"") -> 0.42052176 | D25: =IF(C25="","",IF(C25>=0.85,"🟢 Green",IF(C25>=0.75,"🟡 Yellow","🔴 Red"))) -> 🔴 Red | E25: =IF(COUNTA(C23:C25)<3,"(need 3mo)",IF(AVERAGE(C23:C25)>=0.85,"↑ Improving",IF(AVERAGE(C23:C25)>=0.75,"→ Stable","↓ Declining"))) -> → Stable
A26: SECTION B — Cycle Time (Median) - Baseline=0% - Green; Baseline <=10% - Yellow; Baseline >10%- Red
A27: Cycle Time (Development → Testing → Review → Done) = Start Date → Done Date (days). Enter median for the sprint from JIRA
A28: Sprint ID | B28: Month | C28: Median Cycle Time (days) | D28: Baseline Cycle Time | E28: Δ vs Baseline | F28: Δ% vs Baseline | G28: CT Status
A30: Sprint 1 | B30: January | C30: =ROUND(AVERAGEIF('Team Median Input'!A:A, A30, 'Team Median Input'!J:J),1) -> 5.3 | D30: 5.4 | E30: =IFERROR(IF(C30="","",C30-D30),"") -> -0.1 | F30: =IFERROR(IF(C30="","",C30/D30-1),"") -> -0.018518519 | G30: =IF(F30="","",IF(F30<=0,"🟢 Green",IF(F30<=0.1,"🟡 Yellow","🔴 Red"))) -> 🟢 Green
A31: Sprint 2 | B31: February | C31: =AVERAGEIF('Team Median Input'!A:A, A31, 'Team Median Input'!J:J) -> 5.335 | D31: 5.4 | E31: =IFERROR(IF(C31="","",C31-D31),"") -> -0.065 | F31: =IFERROR(IF(C31="","",C31/D31-1),"") -> -0.012037037 | G31: =IF(F31="","",IF(F31<=0,"🟢 Green",IF(F31<=0.1,"🟡 Yellow","🔴 Red"))) -> 🟢 Green
A32: Sprint 3 | B32: February | C32: =AVERAGEIF('Team Median Input'!A:A, A32, 'Team Median Input'!J:J) -> 3.7225 | D32: 5.4 | E32: =IFERROR(IF(C32="","",C32-D32),"") -> -1.6775 | F32: =IFERROR(IF(C32="","",C32/D32-1),"") -> -0.31064815 | G32: =IF(F32="","",IF(F32<=0,"🟢 Green",IF(F32<=0.1,"🟡 Yellow","🔴 Red"))) -> 🟢 Green
A33: Sprint 4 | B33: March | C33: =AVERAGEIF('Team Median Input'!A:A, A33, 'Team Median Input'!J:J) -> 4.3325 | D33: 5.4 | E33: =IFERROR(IF(C33="","",C33-D33),"") -> -1.0675 | F33: =IFERROR(IF(C33="","",C33/D33-1),"") -> -0.19768519 | G33: =IF(F33="","",IF(F33<=0,"🟢 Green",IF(F33<=0.1,"🟡 Yellow","🔴 Red"))) -> 🟢 Green
A34: Sprint 5 | B34: March | C34: =AVERAGEIF('Team Median Input'!A:A, A34, 'Team Median Input'!J:J) -> 5.7075 | D34: 5.4 | E34: =IFERROR(IF(C34="","",C34-D34),"") -> 0.3075 | F34: =IFERROR(IF(C34="","",C34/D34-1),"") -> 0.056944444 | G34: =IF(F34="","",IF(F34<=0,"🟢 Green",IF(F34<=0.1,"🟡 Yellow","🔴 Red"))) -> 🟡 Yellow
A35: Sprint 6 | B35: March | C35: =AVERAGEIF('Team Median Input'!A:A, A35, 'Team Median Input'!J:J) -> 6.0325 | D35: 5.4 | E35: =IFERROR(IF(C35="","",C35-D35),"") -> 0.6325 | F35: =IFERROR(IF(C35="","",C35/D35-1),"") -> 0.11712963 | G35: =IF(F35="","",IF(F35<=0,"🟢 Green",IF(F35<=0.1,"🟡 Yellow","🔴 Red"))) -> 🔴 Red
A36: Q2 Sprint 1 | B36: April | C36: =AVERAGEIF('Team Median Input'!A:A, A36, 'Team Median Input'!J:J) -> 4.685 | D36: 5.4 | E36: =IFERROR(IF(C36="","",C36-D36),"") -> -0.715 | F36: =IFERROR(IF(C36="","",C36/D36-1),"") -> -0.13240741 | G36: =IF(F36="","",IF(F36<=0,"🟢 Green",IF(F36<=0.1,"🟡 Yellow","🔴 Red"))) -> 🟢 Green
A37: Q2 Sprint 2 | B37: April | C37: =AVERAGEIF('Team Median Input'!A:A, A37, 'Team Median Input'!J:J) -> 4.35 | D37: 5.4 | E37: =IFERROR(IF(C37="","",C37-D37),"") -> -1.05 | F37: =IFERROR(IF(C37="","",C37/D37-1),"") -> -0.19444444 | G37: =IF(F37="","",IF(F37<=0,"🟢 Green",IF(F37<=0.1,"🟡 Yellow","🔴 Red"))) -> 🟢 Green
A38: Q2 Sprint 3 | B38: May | C38: =AVERAGEIF('Team Median Input'!A:A, A38, 'Team Median Input'!J:J) -> 4.1666667 | D38: 5.4 | E38: =IFERROR(IF(C38="","",C38-D38),"") -> -1.2333333 | F38: =IFERROR(IF(C38="","",C38/D38-1),"") -> -0.22839506 | G38: =IF(F38="","",IF(F38<=0,"🟢 Green",IF(F38<=0.1,"🟡 Yellow","🔴 Red"))) -> 🟢 Green
A39: Q2 Sprint 4 | B39: May | C39: =AVERAGEIF('Team Median Input'!A:A, A39, 'Team Median Input'!J:J) -> 5.3025 | D39: 5.4 | E39: =IFERROR(IF(C39="","",C39-D39),"") -> -0.0975 | F39: =IFERROR(IF(C39="","",C39/D39-1),"") -> -0.018055556 | G39: =IF(F39="","",IF(F39<=0,"🟢 Green",IF(F39<=0.1,"🟡 Yellow","🔴 Red"))) -> 🟢 Green
A40: Q2 Sprint 5 | B40: June | C40: =AVERAGEIF('Team Median Input'!A:A, A40, 'Team Median Input'!J:J) -> 5.1 | D40: 5.4 | E40: =IFERROR(IF(C40="","",C40-D40),"") -> -0.3 | F40: =IFERROR(IF(C40="","",C40/D40-1),"") -> -0.055555556 | G40: =IF(F40="","",IF(F40<=0,"🟢 Green",IF(F40<=0.1,"🟡 Yellow","🔴 Red"))) -> 🟢 Green
A41: Q2 Sprint 6 | B41: June | C41: =AVERAGEIF('Team Median Input'!A:A, A41, 'Team Median Input'!J:J) -> 10.14 | D41: 5.4 | E41: =IFERROR(IF(C41="","",C41-D41),"") -> 4.74 | F41: =IFERROR(IF(C41="","",C41/D41-1),"") -> 0.87777778 | G41: =IF(F41="","",IF(F41<=0,"🟢 Green",IF(F41<=0.1,"🟡 Yellow","🔴 Red"))) -> 🔴 Red
E42: =IFERROR(IF(C42="","",C42-D42),"") | F42: =IFERROR(IF(C42="","",C42/D42-1),"") | G42: =IF(F42="","",IF(F42<=0,"🟢 Green",IF(F42<=0.1,"🟡 Yellow","🔴 Red")))
E43: =IFERROR(IF(C43="","",C43-D43),"") | F43: =IFERROR(IF(C43="","",C43/D43-1),"") | G43: =IF(F43="","",IF(F43<=0,"🟢 Green",IF(F43<=0.1,"🟡 Yellow","🔴 Red")))
A47: SECTION B — Development Cycle Time (Median) - Baseline=0% - Green; Baseline <=10% - Yellow; Baseline >10%- Red
A48: Cycle Time (Development → Testing)
A49: Sprint ID | B49: Month | C49: Median Cycle Time (days) | D49: Baseline Cycle Time | E49: Δ vs Baseline | F49: Δ% vs Baseline | G49: CT Status
A50: Sprint 1 | B50: January | C50: =ROUND(AVERAGEIF('Team Median Input'!A:A, A50, 'Team Median Input'!G:G),1) -> 5.2 | D50: 5.2 | E50: =IFERROR(IF(C50="","",C50-D50),"") -> 0 | F50: =IFERROR(IF(C50="","",C50/D50-1),"") -> 0 | G50: =IF(F50="","",IF(F50<=0,"🟢 Green",IF(F50<=0.1,"🟡 Yellow","🔴 Red"))) -> 🟢 Green
A51: Sprint 2 | B51: February | C51: =AVERAGEIF('Team Median Input'!A:A, A51, 'Team Median Input'!G:G) -> 3.765 | D51: 5.2 | E51: =IFERROR(IF(C51="","",C51-D51),"") -> -1.435 | F51: =IFERROR(IF(C51="","",C51/D51-1),"") -> -0.27596154 | G51: =IF(F51="","",IF(F51<=0,"🟢 Green",IF(F51<=0.1,"🟡 Yellow","🔴 Red"))) -> 🟢 Green
A52: Sprint 3 | B52: February | C52: =AVERAGEIF('Team Median Input'!A:A, A52, 'Team Median Input'!G:G) -> 2.785 | D52: 5.2 | E52: =IFERROR(IF(C52="","",C52-D52),"") -> -2.415 | F52: =IFERROR(IF(C52="","",C52/D52-1),"") -> -0.46442308 | G52: =IF(F52="","",IF(F52<=0,"🟢 Green",IF(F52<=0.1,"🟡 Yellow","🔴 Red"))) -> 🟢 Green
A53: Sprint 4 | B53: March | C53: =AVERAGEIF('Team Median Input'!A:A, A53, 'Team Median Input'!G:G) -> 3.01 | D53: 5.2 | E53: =IFERROR(IF(C53="","",C53-D53),"") -> -2.19 | F53: =IFERROR(IF(C53="","",C53/D53-1),"") -> -0.42115385 | G53: =IF(F53="","",IF(F53<=0,"🟢 Green",IF(F53<=0.1,"🟡 Yellow","🔴 Red"))) -> 🟢 Green
A54: Sprint 5 | B54: March | C54: =AVERAGEIF('Team Median Input'!A:A, A54, 'Team Median Input'!G:G) -> 5.03 | D54: 5.2 | E54: =IFERROR(IF(C54="","",C54-D54),"") -> -0.17 | F54: =IFERROR(IF(C54="","",C54/D54-1),"") -> -0.032692308 | G54: =IF(F54="","",IF(F54<=0,"🟢 Green",IF(F54<=0.1,"🟡 Yellow","🔴 Red"))) -> 🟢 Green
A55: Sprint 6 | B55: March | C55: =AVERAGEIF('Team Median Input'!A:A, A55, 'Team Median Input'!G:G) -> 4.1575 | D55: 5.2 | E55: =IFERROR(IF(C55="","",C55-D55),"") -> -1.0425 | F55: =IFERROR(IF(C55="","",C55/D55-1),"") -> -0.20048077 | G55: =IF(F55="","",IF(F55<=0,"🟢 Green",IF(F55<=0.1,"🟡 Yellow","🔴 Red"))) -> 🟢 Green
A56: Q2 Sprint 1 | B56: April | C56: =AVERAGEIF('Team Median Input'!A:A, A56, 'Team Median Input'!G:G) -> 4.15 | D56: 5.2 | E56: =IFERROR(IF(C56="","",C56-D56),"") -> -1.05 | F56: =IFERROR(IF(C56="","",C56/D56-1),"") -> -0.20192308 | G56: =IF(F56="","",IF(F56<=0,"🟢 Green",IF(F56<=0.1,"🟡 Yellow","🔴 Red"))) -> 🟢 Green
A57: Q2 Sprint 2 | B57: April | C57: =AVERAGEIF('Team Median Input'!A:A, A57, 'Team Median Input'!G:G) -> 2.78 | D57: 5.2 | E57: =IFERROR(IF(C57="","",C57-D57),"") -> -2.42 | F57: =IFERROR(IF(C57="","",C57/D57-1),"") -> -0.46538462 | G57: =IF(F57="","",IF(F57<=0,"🟢 Green",IF(F57<=0.1,"🟡 Yellow","🔴 Red"))) -> 🟢 Green
A58: Q2 Sprint 3 | B58: May | C58: =AVERAGEIF('Team Median Input'!A:A, A58, 'Team Median Input'!G:G) -> 3.4 | D58: 5.2 | E58: =IFERROR(IF(C58="","",C58-D58),"") -> -1.8 | F58: =IFERROR(IF(C58="","",C58/D58-1),"") -> -0.34615385 | G58: =IF(F58="","",IF(F58<=0,"🟢 Green",IF(F58<=0.1,"🟡 Yellow","🔴 Red"))) -> 🟢 Green
A59: Q2 Sprint 4 | B59: May | C59: =AVERAGEIF('Team Median Input'!A:A, A59, 'Team Median Input'!G:G) -> 4.2375 | D59: 5.2 | E59: =IFERROR(IF(C59="","",C59-D59),"") -> -0.9625 | F59: =IFERROR(IF(C59="","",C59/D59-1),"") -> -0.18509615 | G59: =IF(F59="","",IF(F59<=0,"🟢 Green",IF(F59<=0.1,"🟡 Yellow","🔴 Red"))) -> 🟢 Green
A60: Q2 Sprint 5 | B60: June | C60: =AVERAGEIF('Team Median Input'!A:A, A60, 'Team Median Input'!G:G) -> 3.7 | D60: 5.2 | E60: =IFERROR(IF(C60="","",C60-D60),"") -> -1.5 | F60: =IFERROR(IF(C60="","",C60/D60-1),"") -> -0.28846154 | G60: =IF(F60="","",IF(F60<=0,"🟢 Green",IF(F60<=0.1,"🟡 Yellow","🔴 Red"))) -> 🟢 Green
A61: Q2 Sprint 6 | B61: June | C61: =AVERAGEIF('Team Median Input'!A:A, A61, 'Team Median Input'!G:G) -> 6.1775 | D61: 5.2 | E61: =IFERROR(IF(C61="","",C61-D61),"") -> 0.9775 | F61: =IFERROR(IF(C61="","",C61/D61-1),"") -> 0.18798077 | G61: =IF(F61="","",IF(F61<=0,"🟢 Green",IF(F61<=0.1,"🟡 Yellow","🔴 Red"))) -> 🔴 Red
A62: Sprint 13 | E62: =IFERROR(IF(C62="","",C62-D62),"") | F62: =IFERROR(IF(C62="","",C62/D62-1),"") | G62: =IF(F62="","",IF(F62<=0,"🟢 Green",IF(F62<=0.1,"🟡 Yellow","🔴 Red")))
A63: Sprint 14 | E63: =IFERROR(IF(C63="","",C63-D63),"") | F63: =IFERROR(IF(C63="","",C63/D63-1),"") | G63: =IF(F63="","",IF(F63<=0,"🟢 Green",IF(F63<=0.1,"🟡 Yellow","🔴 Red")))
A66: SECTION B — QA Cycle Time (Median) - Baseline=0% - Green; Baseline <=10% - Yellow; Baseline >10%- Red
A67: Cycle Time (Testing → Acceptance)
A68: Sprint ID | B68: Month | C68: Median Cycle Time (days) | D68: Baseline Cycle Time | E68: Δ vs Baseline | F68: Δ% vs Baseline | G68: CT Status
A69: Sprint 1 | B69: January | C69: =ROUND(AVERAGEIF('Team Median Input'!A:A, A69, 'Team Median Input'!H:H),1) -> 3.2 | D69: 3.2 | E69: =IFERROR(IF(C69="","",C69-D69),"") -> 0 | F69: =IFERROR(IF(C69="","",C69/D69-1),"") -> 0 | G69: =IF(F69="","",IF(F69<=0,"🟢 Green",IF(F69<=0.1,"🟡 Yellow","🔴 Red"))) -> 🟢 Green
A70: Sprint 2 | B70: February | C70: =AVERAGEIF('Team Median Input'!A:A, A70, 'Team Median Input'!H:H) -> 3.1225 | D70: 3.2 | E70: =IFERROR(IF(C70="","",C70-D70),"") -> -0.0775 | F70: =IFERROR(IF(C70="","",C70/D70-1),"") -> -0.02421875 | G70: =IF(F70="","",IF(F70<=0,"🟢 Green",IF(F70<=0.1,"🟡 Yellow","🔴 Red"))) -> 🟢 Green
A71: Sprint 3 | B71: February | C71: =AVERAGEIF('Team Median Input'!A:A, A71, 'Team Median Input'!H:H) -> 1.24 | D71: 3.2 | E71: =IFERROR(IF(C71="","",C71-D71),"") -> -1.96 | F71: =IFERROR(IF(C71="","",C71/D71-1),"") -> -0.6125 | G71: =IF(F71="","",IF(F71<=0,"🟢 Green",IF(F71<=0.1,"🟡 Yellow","🔴 Red"))) -> 🟢 Green
A72: Sprint 4 | B72: March | C72: =AVERAGEIF('Team Median Input'!A:A, A72, 'Team Median Input'!H:H) -> 1.6925 | D72: 3.2 | E72: =IFERROR(IF(C72="","",C72-D72),"") -> -1.5075 | F72: =IFERROR(IF(C72="","",C72/D72-1),"") -> -0.47109375 | G72: =IF(F72="","",IF(F72<=0,"🟢 Green",IF(F72<=0.1,"🟡 Yellow","🔴 Red"))) -> 🟢 Green
A73: Sprint 5 | B73: March | C73: =AVERAGEIF('Team Median Input'!A:A, A73, 'Team Median Input'!H:H) -> 2.4575 | D73: 3.2 | E73: =IFERROR(IF(C73="","",C73-D73),"") -> -0.7425 | F73: =IFERROR(IF(C73="","",C73/D73-1),"") -> -0.23203125 | G73: =IF(F73="","",IF(F73<=0,"🟢 Green",IF(F73<=0.1,"🟡 Yellow","🔴 Red"))) -> 🟢 Green
A74: Sprint 6 | B74: March | C74: =AVERAGEIF('Team Median Input'!A:A, A74, 'Team Median Input'!H:H) -> 3.675 | D74: 3.2 | E74: =IFERROR(IF(C74="","",C74-D74),"") -> 0.475 | F74: =IFERROR(IF(C74="","",C74/D74-1),"") -> 0.1484375 | G74: =IF(F74="","",IF(F74<=0,"🟢 Green",IF(F74<=0.1,"🟡 Yellow","🔴 Red"))) -> 🔴 Red
A75: Q2 Sprint 1 | B75: April | C75: =AVERAGEIF('Team Median Input'!A:A, A75, 'Team Median Input'!H:H) -> 2.425 | D75: 3.2 | E75: =IFERROR(IF(C75="","",C75-D75),"") -> -0.775 | F75: =IFERROR(IF(C75="","",C75/D75-1),"") -> -0.2421875 | G75: =IF(F75="","",IF(F75<=0,"🟢 Green",IF(F75<=0.1,"🟡 Yellow","🔴 Red"))) -> 🟢 Green
A76: Q2 Sprint 2 | B76: April | C76: =AVERAGEIF('Team Median Input'!A:A, A76, 'Team Median Input'!H:H) -> 2.125 | D76: 3.2 | E76: =IFERROR(IF(C76="","",C76-D76),"") -> -1.075 | F76: =IFERROR(IF(C76="","",C76/D76-1),"") -> -0.3359375 | G76: =IF(F76="","",IF(F76<=0,"🟢 Green",IF(F76<=0.1,"🟡 Yellow","🔴 Red"))) -> 🟢 Green
A77: Q2 Sprint 3 | B77: May | C77: =AVERAGEIF('Team Median Input'!A:A, A77, 'Team Median Input'!H:H) -> 2.5 | D77: 3.2 | E77: =IFERROR(IF(C77="","",C77-D77),"") -> -0.7 | F77: =IFERROR(IF(C77="","",C77/D77-1),"") -> -0.21875 | G77: =IF(F77="","",IF(F77<=0,"🟢 Green",IF(F77<=0.1,"🟡 Yellow","🔴 Red"))) -> 🟢 Green
A78: Q2 Sprint 4 | B78: May | C78: =AVERAGEIF('Team Median Input'!A:A, A78, 'Team Median Input'!H:H) -> 1.835 | D78: 3.2 | E78: =IFERROR(IF(C78="","",C78-D78),"") -> -1.365 | F78: =IFERROR(IF(C78="","",C78/D78-1),"") -> -0.4265625 | G78: =IF(F78="","",IF(F78<=0,"🟢 Green",IF(F78<=0.1,"🟡 Yellow","🔴 Red"))) -> 🟢 Green
A79: Q2 Sprint 5 | B79: June | C79: =AVERAGEIF('Team Median Input'!A:A, A79, 'Team Median Input'!H:H) -> 1.9 | D79: 3.2 | E79: =IFERROR(IF(C79="","",C79-D79),"") -> -1.3 | F79: =IFERROR(IF(C79="","",C79/D79-1),"") -> -0.40625 | G79: =IF(F79="","",IF(F79<=0,"🟢 Green",IF(F79<=0.1,"🟡 Yellow","🔴 Red"))) -> 🟢 Green
A80: Q2 Sprint 6 | B80: June | C80: =AVERAGEIF('Team Median Input'!A:A, A80, 'Team Median Input'!H:H) -> 2.0375 | D80: 3.2 | E80: =IFERROR(IF(C80="","",C80-D80),"") -> -1.1625 | F80: =IFERROR(IF(C80="","",C80/D80-1),"") -> -0.36328125 | G80: =IF(F80="","",IF(F80<=0,"🟢 Green",IF(F80<=0.1,"🟡 Yellow","🔴 Red"))) -> 🟢 Green
A81: Sprint 13 | E81: =IFERROR(IF(C81="","",C81-D81),"") | F81: =IFERROR(IF(C81="","",C81/D81-1),"") | G81: =IF(F81="","",IF(F81<=0,"🟢 Green",IF(F81<=0.1,"🟡 Yellow","🔴 Red")))
A82: Sprint 14 | E82: =IFERROR(IF(C82="","",C82-D82),"") | F82: =IFERROR(IF(C82="","",C82/D82-1),"") | G82: =IF(F82="","",IF(F82<=0,"🟢 Green",IF(F82<=0.1,"🟡 Yellow","🔴 Red")))

Sheet 📐 Formulas
B1: METRIC DEFINITIONS, FORMULAS & THRESHOLDS — Reference
B3: Metric | C3: Formula | D3: 🟡 Green | E3: 🟡 Yellow | F3: 🔴 Red | G3: Frequency / Notes
B4: EAC vs SOW Budget | C4: EAC ÷ SOW Budget Target × 100 | D4: ≤ 100% | E4: 100–105% | F4: > 105% | G4: Monthly. Top drivers required if Yellow/Red.
B5: Monthly Sprint Burn Variance | C5: (Actual Spend − Planned Spend) ÷ Planned Spend × 100 | D5: ≤ ±5% | E5: ±5–10% | F5: > ±10% | G5: Monthly. Log drivers: rework, delays, scope, staffing.
B6: Cost per Story Point — Story Points Delivered | C6: Team Cost ($) ÷ Story Points Delivered (Team SP only) | D6: Stable or ↓ vs baseline | E6: ↑ 5–10% vs baseline | F6: ↑ >10% vs baseline | G6: Monthly; rolling 3-month avg for trend. Baseline = first full sprint month.
B7: Cost per Story Point — Defects delivered | C7: Team Cost ($) ÷ Total SP (Team SP + Defect SP) | D7: Stable or ↓ vs baseline | E7: ↑ 5–10% vs baseline | F7: ↑ >10% vs baseline | G7: Monthly; defect work sized and included. Same baseline as Team.
B8: Commitment Reliability | C8: Total Completed (Stories+Defects+Bugs) ÷ Total Committed × 100 | D8: ≥ 85% | E8: 75–84% | F8: < 75% | G8: Per sprint + monthly rollup + 3-sprint trend.
B9: Cycle Time (Median) | C9: Median(Done Date − In-Progress) across all cards in period | D9: Stable or ↓ vs baseline | E9: ↑ up to 10% vs baseline | F9: ↑ > 10% vs baseline | G9: Per sprint + monthly rollup + 3-sprint trend. Start = first In Progress.
B10: Production Defect Leakage (Severity-Weighted) | C10: Total Prod Defects ÷ All Pre-Prod Defects × 100 | D10: ≤ 10% | E10: 11–15% | F10: > 15% | G10: Monthly + per release/feature. Measured post-deployment.
B11: Rework Ratio | C11: (Story and Standalone Bug Fix Effort ÷ Total Points Delivered) × 100 | D11: ≤ 20% | E11: 21–30% | F11: > 30% | G11: Monthly with rolling trend.
B12: First Time Pass Rate | C12: (Stories Completed w/o any defects ÷ Total stories delivered) × 100 | D12: ≥ 95% | E12: ≥ 85% | F12: < 85% | G12: Monthly with rolling trend.
B14: KEY ASSUMPTIONS & NOTES
B15: Baseline setting | C15: Set the Cost/SP and Cycle Time baselines ONCE in the yellow-highlighted cells on first use. These persist as the reference for all RAG calculations.
B16: Defect sizing | C16: Defects must be estimated in story points BEFORE the sprint to be included in Cost/SP program calculation and sprint commitment.
B17: Severity weighting | C17: Use weights in Quality sheet if we decide to use them for severity scales.
B18: Rework Effort | C18: Capture Story Defects and Standalone Bug Fix Points/counts ÷ Total Story Points in JIRA tool for accurate Rework Ratio.
B19: Cycle time source | C19: Pull median cycle time from JIRA (Control Charts). Exclude blocked time if used for any reason

Sheet Team Sprints Input
A1: Team Wise Sprint Input
A2: Sprint ID | B2: Team | C2: Sprint Start Date | D2: Sprint End Date | E2: Month | F2: Stories Planned | G2: Sprint Defects Planned | H2: Standalone Bugs Planned | I2: Stories Completed | J2: Story Defects Completed | K2: Standalone Bugs Completed | L2: Total Planned | M2: Total Completed | N2: Baseline Velocity | O2: Rework Ratio | P2: Comments
A3: Sprint 1 | B3: Team 1 | C3: 46029 | D3: 46042 | E3: January | F3: 0 | G3: 0 | H3: 0 | I3: 0 | J3: 0 | K3: 0 | L3: =F3+H3 -> 0 | M3: =I3+K3 -> 0 | O3: =SUM(J3:K3)/M3 -> #DIV/0!
A4: Sprint 1 | B4: Team 2 | C4: 46029 | D4: 46042 | E4: January | F4: 48 | G4: 13 | H4: 0 | I4: 30 | J4: 5 | K4: 0 | L4: =F4+H4 -> 48 | M4: =I4+K4 -> 30 | N4: 45 | O4: =K4/M4 -> 0 | P4: Lot of cards spilled over to pending testing and defects
A5: Sprint 1 | B5: Team 3 | C5: 46029 | D5: 46042 | E5: January | F5: 120 | G5: 8 | H5: 10 | I5: 34 | J5: 1 | K5: 4 | L5: =F5+H5 -> 130 | M5: =I5+K5 -> 38 | N5: 36 | O5: =K5/M5 -> 0.10526316 | P5: All testing pending cards due to CSEI-11111 defect .Net Update Status Types testing was blocked. Save Token for Org Blocked due to CoreSuite not available with the functionality. COA tiles cards testing was blocked due to Experience Team misconfigured files in .net
A6: Sprint 1 | B6: Team 4 | C6: 46029 | D6: 46042 | E6: January | F6: 82 | G6: 3 | H6: 0 | I6: 48 | J6: 2 | K6: 0 | L6: =F6+H6 -> 82 | M6: =I6+K6 -> 48 | N6: 35 | O6: =K6/M6 -> 0 | P6: Few are CIM related cards and few are reports which are still in analysis phase
A7: Sprint 2 | B7: Team 1 | C7: 46043 | D7: 46056 | E7: February | F7: 352 | G7: 33 | H7: 50 | I7: 260 | J7: 28 | K7: 26 | L7: =F7+H7 -> 402 | M7: =I7+K7 -> 286 | N7: 200 | O7: =K7/M7 -> 0.090909091
A8: Sprint 2 | B8: Team 2 | C8: 46043 | D8: 46056 | E8: February | F8: 63 | G8: 5 | H8: 2 | I8: 56 | J8: 9 | K8: 2 | L8: =F8+H8 -> 65 | M8: =I8+K8 -> 58 | N8: 45 | O8: =K8/M8 -> 0.034482759
A9: Sprint 2 | B9: Team 3 | C9: 46043 | D9: 46056 | E9: February | F9: 104 | G9: 2 | H9: 12 | I9: 36 | J9: 3 | K9: 6 | L9: =F9+H9 -> 116 | M9: =I9+K9 -> 42 | N9: 36 | O9: =K9/M9 -> 0.14285714 | P9: Due to CSEI-11111 defect .Net Update Status Types testing was blocked CSEI-10456 defect blocked few mendix cards for organization tokenid Payment Center .Net cards were blocked due to Policy Inquiry API schema mismatch for PreActive OneTime GuestPayment - New Work in Payment Centerweb, MDM - Policy Status issues identified at last moment
A10: Sprint 2 | B10: Team 4 | C10: 46043 | D10: 46056 | E10: February | F10: 69 | G10: 0 | H10: 0 | I10: 18 | J10: 1 | K10: 0 | L10: =F10+H10 -> 69 | M10: =I10+K10 -> 18 | N10: 35 | O10: =K10/M10 -> 0 | P10: Spill over mostly data suit reports
A11: Sprint 3 | B11: Team 1 | C11: 46057 | D11: 46070 | E11: February | F11: =319-113 -> 206 | G11: 20 | H11: =61+52 -> 113 | I11: =105-52 -> 53 | J11: 2 | K11: 52 | L11: =F11+H11 -> 319 | M11: =I11+K11 -> 105 | N11: 200 | O11: =K11/M11 -> 0.4952381
A12: Sprint 3 | B12: Team 2 | C12: 46057 | D12: 46070 | E12: February | F12: 61 | G12: 7 | H12: 4 | I12: 35 | J12: 8 | K12: 4 | L12: =F12+H12 -> 65 | M12: =I12+K12 -> 39 | N12: 45 | O12: =K12/M12 -> 0.1025641 | P12: Due to testing spillover and review pending
A13: Sprint 3 | B13: Team 3 | C13: 46057 | D13: 46070 | E13: February | F13: 83 | G13: 0 | H13: 26 | I13: 16 | J13: 0 | K13: 18 | L13: =F13+H13 -> 109 | M13: =I13+K13 -> 34 | N13: 36 | O13: =K13/M13 -> 0.52941176 | P13: Due to CSEI-11111 defect .Net Update Status Types testing was blocked.
A14: Sprint 3 | B14: Team 4 | C14: 46057 | D14: 46070 | E14: February | F14: =53+36 -> 89 | G14: 4 | H14: 1 | I14: 36 | J14: 0 | K14: 1 | L14: =F14+H14 -> 90 | M14: =I14+K14 -> 37 | N14: 35 | O14: =K14/M14 -> 0.027027027
A15: Sprint 4 | B15: Team 1 | C15: 46071 | D15: 46084 | E15: March | F15: =454-132 -> 322 | G15: 2 | H15: =28+104 -> 132 | I15: =246-104 -> 142 | J15: 19 | K15: 104 | L15: =F15+H15 -> 454 | M15: =I15+K15 -> 246 | N15: 200 | O15: =K15/M15 -> 0.42276423
A16: Sprint 4 | B16: Team 2 | C16: 46071 | D16: 46084 | E16: March | F16: 80 | G16: 11 | H16: 7 | I16: 69 | J16: 13 | K16: 7 | L16: =F16+H16 -> 87 | M16: =I16+K16 -> 76 | N16: 45 | O16: =K16/M16 -> 0.092105263
A17: Sprint 4 | B17: Team 3 | C17: 46071 | D17: 46084 | E17: March | F17: 91 | G17: 3 | H17: 17 | I17: 56 | J17: 6 | K17: 14 | L17: =F17+H17 -> 108 | M17: =I17+K17 -> 70 | N17: 36 | O17: =K17/M17 -> 0.2 | P17: Integration cards were spilled due to dependency on CSEI-7531. still not delivered Bene related mendix cards are spilled due to integration card dependency which are planned in SP5
A18: Sprint 4 | B18: Team 4 | C18: 46071 | D18: 46084 | E18: March | F18: =67+45 -> 112 | G18: 1 | H18: 2 | I18: 45 | J18: 5 | K18: 2 | L18: =F18+H18 -> 114 | M18: =I18+K18 -> 47 | N18: 35 | O18: =K18/M18 -> 0.042553191 | P18: Data suite Report cards and cards related for Fund file are spilled over due to pending requirement
A19: Sprint 5 | B19: Team 1 | C19: 46085 | D19: 46098 | E19: March | F19: 369 | G19: 3 | H19: 62 | I19: 194 | J19: 25 | K19: 43 | L19: =F19+H19 -> 431 | M19: =I19+K19 -> 237 | N19: 200 | O19: =K19/M19 -> 0.1814346
A20: Sprint 5 | B20: Team 2 | C20: 46085 | D20: 46098 | E20: March | F20: 75 | G20: 8 | H20: 9 | I20: 39 | J20: 4 | K20: 9 | L20: =F20+H20 -> 84 | M20: =I20+K20 -> 48 | N20: 45 | O20: =K20/M20 -> 0.1875
A21: Sprint 5 | B21: Team 3 | C21: 46085 | D21: 46098 | E21: March | F21: 91 | G21: 1 | H21: 21 | I21: 28 | J21: 1 | K21: 8 | L21: =F21+H21 -> 112 | M21: =I21+K21 -> 36 | N21: 36 | O21: =K21/M21 -> 0.22222222
A22: Sprint 5 | B22: Team 4 | C22: 46085 | D22: 46098 | E22: March | F22: 93 | G22: 1 | H22: 0 | I22: 30 | J22: 4 | K22: 0 | L22: =F22+H22 -> 93 | M22: =I22+K22 -> 30 | N22: 35 | O22: =K22/M22 -> 0
A23: Sprint 6 | B23: Team 1 | C23: 46099 | D23: 46112 | E23: March | F23: 281 | G23: 19 | H23: 43 | I23: 73 | J23: 11 | K23: 25 | L23: =F23+H23 -> 324 | M23: =I23+K23 -> 98 | N23: 200 | O23: =K23/M23 -> 0.25510204 | P23: BRP for multiple days. Reinstatement and conversion which are less priority cards are spilled over.
A24: Sprint 6 | B24: Team 2 | C24: 46099 | D24: 46112 | E24: March | F24: 93 | G24: 7 | H24: 3 | I24: 49 | J24: 7 | K24: 2 | L24: =F24+H24 -> 96 | M24: =I24+K24 -> 51 | N24: 45 | O24: =K24/M24 -> 0.039215686 | P24: Cards are spilled over due to Status not getting updated
A25: Sprint 6 | B25: Team 3 | C25: 46099 | D25: 46112 | E25: March | F25: 68 | G25: 0 | H25: 18 | I25: 13 | J25: 4 | K25: 12 | L25: =F25+H25 -> 86 | M25: =I25+K25 -> 25 | N25: 36 | O25: =K25/M25 -> 0.48 | P25: BRP was there for 2 days. Team had tempus issues multiple times so 3 defects belong to it. Status cards are blocked due to CoreSuite issues. Token ID, RNID company cards defects are fixed at the end of the sprint by Team 1.
A26: Sprint 6 | B26: Team 4 | C26: 46099 | D26: 46112 | E26: March | F26: 78 | G26: 0 | H26: 0 | I26: 37 | J26: 1 | K26: 0 | L26: =F26+H26 -> 78 | M26: =I26+K26 -> 37 | N26: 35 | O26: =K26/M26 -> 0
A27: Q2 Sprint 1 | B27: Team 1 | C27: 46113 | D27: 46126 | E27: April | F27: 308 | G27: 8 | H27: 38 | I27: 115 | J27: 45 | K27: 26 | L27: =F27+H27 -> 346 | M27: =I27+K27 -> 141 | N27: 200 | O27: =K27/M27 -> 0.18439716
A28: Q2 Sprint 1 | B28: Team 2 | C28: 46113 | D28: 46126 | E28: April | F28: 116 | G28: 4 | H28: 2 | I28: 52 | J28: 11 | K28: 2 | L28: =F28+H28 -> 118 | M28: =I28+K28 -> 54 | N28: 45 | O28: =K28/M28 -> 0.037037037
A29: Q2 Sprint 1 | B29: Team 3 | C29: 46113 | D29: 46126 | E29: April | F29: 113 | G29: 0 | H29: 18 | I29: 57 | J29: 0 | K29: 8 | L29: =F29+H29 -> 131 | M29: =I29+K29 -> 65 | N29: 36 | O29: =K29/M29 -> 0.12307692
A30: Q2 Sprint 1 | B30: Team 4 | C30: 46113 | D30: 46126 | E30: April | F30: 97 | G30: 0 | H30: 1 | I30: 46 | J30: 1 | K30: 1 | L30: =F30+H30 -> 98 | M30: =I30+K30 -> 47 | N30: 35 | O30: =K30/M30 -> 0.021276596
A31: Q2 Sprint 2 | B31: Team 1 | C31: 46127 | D31: 46140 | E31: April | F31: 325 | G31: 1 | H31: 121 | I31: 35 | J31: 6 | K31: 90 | L31: =F31+H31 -> 446 | M31: =I31+K31 -> 125 | N31: 200 | O31: =K31/M31 -> 0.72 | P31: most of the defects were related to forms
A32: Q2 Sprint 2 | B32: Team 2 | C32: 46127 | D32: 46140 | E32: April | F32: 143 | G32: 11 | H32: 13 | I32: 47 | J32: 4 | K32: 8 | L32: =F32+H32 -> 156 | M32: =I32+K32 -> 55 | N32: 45 | O32: =K32/M32 -> 0.14545455 | P32: Team worked on more defects leading up to Final Expense Pilot release
A33: Q2 Sprint 2 | B33: Team 3 | C33: 46127 | D33: 46140 | E33: April | F33: 112 | G33: 0 | H33: 10 | I33: 24 | J33: 1 | K33: 3 | L33: =F33+H33 -> 122 | M33: =I33+K33 -> 27 | N33: 36 | O33: =K33/M33 -> 0.11111111
A34: Q2 Sprint 2 | B34: Team 4 | C34: 46127 | D34: 46140 | E34: April | F34: 68 | G34: 1 | H34: 1 | I34: 30 | J34: 0 | K34: 1 | L34: =F34+H34 -> 69 | M34: =I34+K34 -> 31 | N34: 35 | O34: =K34/M34 -> 0.032258065
A35: Q2 Sprint 3 | B35: Team 1 | C35: 46141 | D35: 46154 | E35: May | F35: 260 | G35: 0 | H35: 76 | I35: 37 | J35: 2 | K35: 35 | L35: =F35+H35 -> 336 | M35: =I35+K35 -> 72 | N35: 35 | O35: =K35/M35 -> 0.48611111
A36: Q2 Sprint 3 | B36: Team 2 | C36: 46141 | D36: 46154 | E36: May | F36: 164 | G36: 4 | H36: 26 | I36: 86 | J36: 24 | K36: 23 | L36: =F36+H36 -> 190 | M36: =I36+K36 -> 109 | N36: 35 | O36: =K36/M36 -> 0.21100917 | P36: Team worked on more defects leading up to Final Expense Pilot release
A37: Q2 Sprint 3 | B37: Team 3 | C37: 46141 | D37: 46154 | E37: May | F37: 83 | G37: 0 | H37: 6 | I37: 34 | J37: 4 | K37: 3 | L37: =F37+H37 -> 89 | M37: =I37+K37 -> 37 | N37: 35 | O37: =K37/M37 -> 0.081081081
A38: Q2 Sprint 3 | B38: Team 4 | C38: 46141 | D38: 46154 | E38: May | F38: 79 | G38: 1 | H38: 0 | I38: 50 | J38: 2 | K38: 0 | L38: =F38+H38 -> 79 | M38: =I38+K38 -> 50 | N38: 35 | O38: =K38/M38 -> 0
A39: Q2 Sprint 4 | B39: Team 1 | C39: 46155 | D39: 46168 | E39: May | F39: 209 | G39: 0 | H39: 94 | I39: 67 | J39: 14 | K39: 66 | L39: =F39+H39 -> 303 | M39: =I39+K39 -> 133 | N39: 35 | O39: =K39/M39 -> 0.4962406 | P39: Majorly worked on Release 1.1 and 1.2 activities
A40: Q2 Sprint 4 | B40: Team 2 | C40: 46155 | D40: 46168 | E40: May | F40: 137 | G40: 11 | H40: 26 | I40: 57 | J40: 6 | K40: 18 | L40: =F40+K40 -> 155 | M40: =I40+K40 -> 75 | N40: 35 | O40: =K40/M40 -> 0.24 | P40: Team worked on more defects leading up to Final Expense Pilot release
A41: Q2 Sprint 4 | B41: Team 3 | C41: 46155 | D41: 46168 | E41: May | F41: 91 | G41: 0 | H41: 3 | I41: 13 | J41: 0 | K41: 1 | L41: =F41+H41 -> 94 | M41: =I41+K41 -> 14 | N41: 35 | O41: =K41/M41 -> 0.071428571 | P41: Mendix cards are blocked due to 1125 UWPro Notes issues, Integration card are blocked, simulate premium doesnt suffice requirements
A42: Q2 Sprint 4 | B42: Team 4 | C42: 46155 | D42: 46168 | E42: May | F42: 48 | G42: 0 | H42: 5 | I42: 10 | J42: 0 | K42: 5 | L42: =F42+H42 -> 53 | M42: =I42+K42 -> 15 | N42: 35 | O42: =K42/M42 -> 0.33333333 | P42: Team worked on more defects in this sprint. File Integration cards had 1 issues ,also 2 issues with external team (CIM team) . File integration cards spilled over due to time taken in analysis and coordination
A43: Q2 Sprint 5 | B43: Team 1 | C43: 46169 | D43: 46182 | E43: June | F43: 128 | G43: 4 | H43: 100 | I43: 58 | J43: 10 | K43: 83 | L43: =F43+H43 -> 228 | M43: =I43+K43 -> 141 | N43: 35 | O43: =K43/M43 -> 0.58865248 | P43: Team worked on more bugs when compared to previous sprints as part of recent releases hance the rework ratio increases
A44: Q2 Sprint 5 | B44: Team 2 | C44: 46169 | D44: 46182 | E44: June | F44: 95 | G44: 3 | H44: 22 | I44: 62 | J44: 17 | K44: 17 | L44: =F44+H44 -> 117 | M44: =I44+K44 -> 79 | N44: 35 | O44: =K44/M44 -> 0.21518987 | P44: Team worked on more defects leading up to Final Expense Pilot release
A45: Q2 Sprint 5 | B45: Team 3 | C45: 46169 | D45: 46182 | E45: June | F45: 106 | G45: 2 | H45: 11 | I45: 34 | J45: 1 | K45: 4 | L45: =F45+H45 -> 117 | M45: =I45+K45 -> 38 | N45: 35 | O45: =K45/M45 -> 0.10526316
A46: Q2 Sprint 5 | B46: Team 4 | C46: 46169 | D46: 46182 | E46: June | F46: 68 | G46: 0 | H46: 0 | I46: 31 | J46: 0 | K46: 0 | L46: =F46+H46 -> 68 | M46: =I46+K46 -> 31 | N46: 35 | O46: =K46/M46 -> 0
A47: Q2 Sprint 6 | B47: Team 1 | C47: 46183 | D47: 46196 | E47: June | F47: 151 | G47: 0 | H47: 118 | I47: 48 | J47: 2 | K47: 61 | L47: =F47+H47 -> 269 | M47: =I47+K47 -> 109 | N47: 35 | O47: =K47/M47 -> 0.55963303 | P47: Team worked on more bugs when compared to previous sprints as part of recent releases hance the rework ratio increases
A48: Q2 Sprint 6 | B48: Team 2 | C48: 46183 | D48: 46196 | E48: June | F48: 86 | G48: 0 | H48: 13 | I48: 24 | J48: 2 | K48: 9 | L48: =F48+H48 -> 99 | M48: =I48+K48 -> 33 | N48: 35 | O48: =K48/M48 -> 0.27272727 | P48: Team worked on more defects leading up to Final Expense Pilot release
A49: Q2 Sprint 6 | B49: Team 3 | C49: 46183 | D49: 46196 | E49: June | F49: 96 | G49: 0 | H49: 13 | I49: 19 | J49: 3 | K49: 3 | L49: =F49+H49 -> 109 | M49: =I49+K49 -> 22 | N49: 35 | O49: =K49/M49 -> 0.13636364 | P49: Team 3 QA is testing priority cards for FE portals and other cards are spilled over. Print cards are spilled over due to A&D
A50: Q2 Sprint 6 | B50: Team 4 | C50: 46183 | D50: 46196 | E50: June | F50: 68 | G50: 1 | H50: 0 | I50: 31 | J50: 0 | K50: 0 | L50: =F50+H50 -> 68 | M50: =I50+K50 -> 31 | N50: 35 | O50: =K50/M50 -> 0 | P50: Reports related cards are spilled over
C54: Sprint ID | D54: Team 1 | E54: Team 2 | F54: Team 3 | G54: Team 4
C55: Sprint 1 | D55: NA | E55: 0 | F55: 0.10526316 | G55: 0
C56: Sprint 2 | D56: 0.090909091 | E56: 0.034482759 | F56: 0.14285714 | G56: 0
C57: Sprint 3 | D57: 0.4952381 | E57: 0.1025641 | F57: 0.52941176 | G57: 0.027027027
C58: Sprint 4 | D58: 0.42276423 | E58: 0.092105263 | F58: 0.2 | G58: 0.042553191
C59: Sprint 5 | D59: 0.1814346 | E59: 0.1875 | F59: 0.22222222 | G59: 0
C60: Sprint 6 | D60: 0.25510204 | E60: 0.039215686 | F60: 0.48 | G60: 0
C61: Q2 Sprint 1 | D61: 0.18439716 | E61: 0.037037037 | F61: 0.12307692 | G61: 0.021276596
C62: Q2 Sprint 2 | D62: 0.72 | E62: 0.14545455 | F62: 0.11111111 | G62: 0.032258065
C63: Q2 Sprint 3 | D63: 0.48611111 | E63: 0.21100917 | F63: 0.081081081 | G63: 0
C64: Q2 Sprint 4 | D64: 0.4962406 | E64: 0.24 | F64: 0.071428571 | G64: 0.33333333

Sheet VAM Team Sprint-CostperSprint
A1: Sprint ID | B1: Team | C1: Sprint Start Date | D1: Sprint End Date | E1: Month | F1: Stories Completed | G1: Story Defects Completed | H1: Standalone Bugs Completed | I1: Total Completed | J1: Total Developers
A2: Sprint 1 | B2: Team 1 | C2: 46029 | D2: 46042 | E2: January | F2: 0 | G2: 0 | H2: 0 | I2: =F2+H2 -> 0
A3: Sprint 1 | B3: Team 2 | C3: 46029 | D3: 46042 | E3: January | F3: 21 | G3: 5 | H3: 0 | I3: =F3+H3 -> 21 | J3: 4
A4: Sprint 1 | B4: Team 3 | C4: 46029 | D4: 46042 | E4: January | F4: 34 | G4: 1 | H4: 4 | I4: =F4+H4 -> 38
A5: Sprint 1 | B5: Team 4 | C5: 46029 | D5: 46042 | E5: January | F5: 25 | G5: 2 | H5: 0 | I5: =F5+H5 -> 25
A6: Sprint 2 | B6: Team 1 | C6: 46043 | D6: 46056 | E6: February | F6: 67 | G6: 23 | H6: 14 | I6: =F6+H6 -> 81
A7: Sprint 2 | B7: Team 2 | C7: 46043 | D7: 46056 | E7: February | F7: 42 | G7: 9 | H7: 2 | I7: =F7+H7 -> 44 | J7: 4
A8: Sprint 2 | B8: Team 3 | C8: 46043 | D8: 46056 | E8: February | F8: 36 | G8: 3 | H8: 6 | I8: =F8+H8 -> 42
A9: Sprint 2 | B9: Team 4 | C9: 46043 | D9: 46056 | E9: February | F9: 11 | G9: 1 | H9: 0 | I9: =F9+H9 -> 11
A10: Sprint 3 | B10: Team 1 | C10: 46057 | D10: 46070 | E10: February | F10: 22 | G10: 2 | H10: 43 | I10: =F10+H10 -> 65
A11: Sprint 3 | B11: Team 2 | C11: 46057 | D11: 46070 | E11: February | F11: 25 | G11: 8 | H11: 4 | I11: =F11+H11 -> 29 | J11: 4
A12: Sprint 3 | B12: Team 3 | C12: 46057 | D12: 46070 | E12: February | F12: 16 | G12: 0 | H12: 18 | I12: =F12+H12 -> 34
A13: Sprint 3 | B13: Team 4 | C13: 46057 | D13: 46070 | E13: February | F13: 18 | G13: 0 | H13: 1 | I13: =F13+H13 -> 19
A14: Sprint 4 | B14: Team 1 | C14: 46071 | D14: 46084 | E14: March | F14: 92 | G14: 13 | H14: 85 | I14: =F14+H14 -> 177
A15: Sprint 4 | B15: Team 2 | C15: 46071 | D15: 46084 | E15: March | F15: 44 | G15: 13 | H15: 7 | I15: =F15+H15 -> 51 | J15: 5
A16: Sprint 4 | B16: Team 3 | C16: 46071 | D16: 46084 | E16: March | F16: 56 | G16: 6 | H16: 14 | I16: =F16+H16 -> 70
A17: Sprint 4 | B17: Team 4 | C17: 46071 | D17: 46084 | E17: March | F17: 23 | G17: 5 | H17: 2 | I17: =F17+H17 -> 25
A18: Sprint 5 | B18: Team 1 | C18: 46085 | D18: 46098 | E18: March | F18: 63 | G18: 12 | H18: 20 | I18: =F18+H18 -> 83
A19: Sprint 5 | B19: Team 2 | C19: 46085 | D19: 46098 | E19: March | F19: 22 | G19: 4 | H19: 9 | I19: =F19+H19 -> 31 | J19: 5
A20: Sprint 5 | B20: Team 3 | C20: 46085 | D20: 46098 | E20: March | F20: 28 | G20: 1 | H20: 8 | I20: =F20+H20 -> 36
A21: Sprint 5 | B21: Team 4 | C21: 46085 | D21: 46098 | E21: March | F21: 14 | G21: 4 | H21: 0 | I21: =F21+H21 -> 14
A22: Sprint 6 | B22: Team 1 | C22: 46099 | D22: 46112 | E22: March | F22: 38 | G22: 8 | H22: 7 | I22: =F22+H22 -> 45
A23: Sprint 6 | B23: Team 2 | C23: 46099 | D23: 46112 | E23: March | F23: 13 | G23: 7 | H23: 1 | I23: =F23+H23 -> 14 | J23: 5
A24: Sprint 6 | B24: Team 3 | C24: 46099 | D24: 46112 | E24: March | F24: 13 | G24: 4 | H24: 12 | I24: =F24+H24 -> 25
A25: Sprint 6 | B25: Team 4 | C25: 46099 | D25: 46112 | E25: March | F25: 29 | G25: 1 | H25: 0 | I25: =F25+H25 -> 29
A26: Q2 Sprint 1 | B26: Team 1 | C26: 46113 | D26: 46126 | E26: April | F26: 83 | G26: 27 | H26: 11 | I26: =F26+H26 -> 94
A27: Q2 Sprint 1 | B27: Team 2 | C27: 46113 | D27: 46126 | E27: April | F27: 38 | G27: 11 | H27: 2 | I27: =F27+H27 -> 40
A28: Q2 Sprint 1 | B28: Team 3 | C28: 46113 | D28: 46126 | E28: April | F28: 57 | G28: 0 | H28: 8 | I28: =F28+H28 -> 65
A29: Q2 Sprint 1 | B29: Team 4 | C29: 46113 | D29: 46126 | E29: April | F29: 20 | G29: 1 | H29: 1 | I29: =F29+H29 -> 21
A30: Q2 Sprint 2 | B30: Team 1 | C30: 46127 | D30: 46140 | E30: April | F30: 11 | G30: 0 | H30: 46 | I30: =F30+H30 -> 57
A31: Q2 Sprint 2 | B31: Team 2 | C31: 46127 | D31: 46140 | E31: April | F31: 35 | G31: 4 | H31: 8 | I31: =F31+H31 -> 43
A32: Q2 Sprint 2 | B32: Team 3 | C32: 46127 | D32: 46140 | E32: April | F32: 24 | G32: 1 | H32: 3 | I32: =F32+H32 -> 27
A33: Q2 Sprint 2 | B33: Team 4 | C33: 46127 | D33: 46140 | E33: April | F33: 14 | G33: 0 | H33: 0 | I33: =F33+H33 -> 14
A34: Q2 Sprint 3 | B34: Team 1 | C34: 46141 | D34: 46154 | E34: May | F34: 14 | G34: 0 | H34: 15 | I34: =F34+H34 -> 29
A35: Q2 Sprint 3 | B35: Team 2 | C35: 46141 | D35: 46154 | E35: May | F35: 59 | G35: 24 | H35: 23 | I35: =F35+H35 -> 82
... A49: Q2 Sprint 6 | B49: Team 4 | C49: 46183 | D49: 46196 | E49: June | F49: 22 | G49: 0 | H49: 0 | I49: =F49+H49 -> 22

Sheet Team Median Input
A1: Sprint ID | B1: Sprint Start Date | C1: Sprint End Date | D1: Team | E1: Month | F1: BA to Dev | G1: Median Cycle Time (days) - Dev to Test | H1: Median Cycle Time (days) - Test to Acceptance | I1: Median Cycle Time (days) - Acceptance to Done | J1: Median Cycle Time (days) | K1: Baseline Cycle Time | L1: Δ vs Baseline | M1: Δ% vs Baseline
A2: Sprint 1 | B2: 46029 | C2: 46042 | D2: Team 2 | E2: January | G2: 4.3 | H2: 0.6 | I2: 0.01 | J2: 5.3 | K2: 5.8 | L2: =IFERROR(IF(J2="","",J2-K2),"") -> -0.5 | M2: =IFERROR(IF(J2="","",J2/K2-1),"") -> -0.086206897
A3: Sprint 2 | B3: 46043 | C3: 46056 | D3: Team 2 | E3: February | G3: 6.2 | H3: 2.2 | I3: 0.23 | J3: 7.11 | K3: =$K$21 -> 0 | L3: =IFERROR(IF(J3="","",J3-K3),"") -> 7.11 | M3: =IFERROR(IF(J3="","",J3/K3-1),"")
A4: Sprint 3 | B4: 46057 | C4: 46070 | D4: Team 2 | E4: February | G4: 5.7 | H4: 0.7 | I4: 0.3 | J4: 5.16 | K4: =$K$21 -> 0 | L4: =IFERROR(IF(J4="","",J4-K4),"") -> 5.16 | M4: =IFERROR(IF(J4="","",J4/K4-1),"")
A5: Sprint 4 | B5: 46071 | C5: 46084 | D5: Team 2 | E5: March | G5: 2.6 | H5: 1.2 | I5: 0.3 | J5: 4.3 | K5: =$K$21 -> 0 | L5: =IFERROR(IF(J5="","",J5-K5),"") -> 4.3 | M5: =IFERROR(IF(J5="","",J5/K5-1),"")
A6: Sprint 1 | B6: 46029 | C6: 46042 | D6: Team 3 | E6: January | G6: 7.2 | H6: 7.4 | I6: 0.3 | J6: 7.4 | K6: 5.1 | L6: =IFERROR(IF(J6="","",J6-K6),"") -> 2.3 | M6: =IFERROR(IF(J6="","",J6/K6-1),"") -> 0.45098039
A7: Sprint 2 | B7: 46043 | C7: 46056 | D7: Team 3 | E7: February | G7: 5.5 | H7: 4.5 | I7: 0.4 | J7: 6 | K7: 5.1 | L7: =IFERROR(IF(J7="","",J7-K7),"") -> 0.9 | M7: =IFERROR(IF(J7="","",J7/K7-1),"") -> 0.17647059
A8: Sprint 3 | B8: 46057 | C8: 46070 | D8: Team 3 | E8: February | G8: 1.22 | H8: 1.15 | I8: 0.3 | J8: 2.4 | K8: 5.1 | L8: =IFERROR(IF(J8="","",J8-K8),"") -> -2.7 | M8: =IFERROR(IF(J8="","",J8/K8-1),"") -> -0.52941176
A9: Sprint 4 | B9: 46071 | C9: 46084 | D9: Team 3 | E9: March | G9: 2.1 | H9: 4.2 | I9: 0.1 | J9: 4.13 | K9: 5.1 | L9: =IFERROR(IF(J9="","",J9-K9),"") -> -0.97 | M9: =IFERROR(IF(J9="","",J9/K9-1),"") -> -0.19019608
A10: Sprint 1 | B10: 46029 | C10: 46042 | D10: Team 4 | E10: January | G10: 6.1 | H10: 3.8 | I10: 2.5 | J10: 5.4 | K10: 4.7 | L10: =IFERROR(IF(J10="","",J10-K10),"") -> 0.7 | M10: =IFERROR(IF(J10="","",J10/K10-1),"") -> 0.14893617
A11: Sprint 2 | B11: 46043 | C11: 46056 | D11: Team 4 | E11: February | G11: 0.16 | H11: 3.6 | I11: 2.4 | J11: 4.1 | K11: 4.7 | L11: =IFERROR(IF(J11="","",J11-K11),"") -> -0.6 | M11: =IFERROR(IF(J11="","",J11/K11-1),"") -> -0.12765957
A12: Sprint 3 | B12: 46057 | C12: 46070 | D12: Team 4 | E12: February | G12: 1.12 | H12: 1.21 | I12: 1.21 | J12: 3.23 | K12: 4.7 | L12: =IFERROR(IF(J12="","",J12-K12),"") -> -1.47 | M12: =IFERROR(IF(J12="","",J12/K12-1),"") -> -0.31276596
A13: Sprint 4 | B13: 46071 | C13: 46084 | D13: Team 4 | E13: March | G13: 4.19 | H13: 1.22 | I13: 1 | J13: 4.2 | K13: 4.7 | L13: =IFERROR(IF(J13="","",J13-K13),"") -> -0.5 | M13: =IFERROR(IF(J13="","",J13/K13-1),"") -> -0.10638298
A14: Sprint 1 | B14: 46029 | C14: 46042 | D14: Team 1 | E14: January | F14: 0.1 days | G14: 3.15 | H14: 1.13 | I14: 0.15 | J14: 3.18 | K14: 4 | L14: =IFERROR(IF(J14="","",J14-K14),"") -> -0.82
A15: Sprint 2 | B15: 46043 | C15: 46056 | D15: Team 1 | E15: February | F15: 0.1 days | G15: 3.2 | H15: 2.19 | I15: 1.7 | J15: 4.13 | K15: 4 | L15: =IFERROR(IF(J15="","",J15-K15),"") -> 0.13
A16: Sprint 3 | B16: 46057 | C16: 46070 | D16: Team 1 | E16: February | F16: 2.23 days | G16: 3.1 | H16: 1.9 | I16: 0.1 | J16: 4.1 | K16: 4 | L16: =IFERROR(IF(J16="","",J16-K16),"") -> 0.1
A17: Sprint 4 | B17: 46071 | C17: 46084 | D17: Team 1 | E17: March | F17: 1.2 days | G17: 3.15 | H17: 0.15 | I17: 0.9 | J17: 4.7 | K17: 4 | L17: =IFERROR(IF(J17="","",J17-K17),"") -> 0.7
A18: Sprint 5 | B18: 46085 | C18: 46098 | D18: Team 1 | E18: March | G18: 4.12 | H18: 1.14 | I18: 0.18 | J18: 5.23
A19: Sprint 5 | B19: 46085 | C19: 46098 | D19: Team 2 | E19: March | G19: 5.3 | H19: 1 | I19: 1.37 | J19: 5.3
A20: Sprint 5 | B20: 46085 | C20: 46098 | D20: Team 3 | E20: March | G20: 7.1 | H20: 4.19 | I20: 0.22 | J20: 7.2
A21: Sprint 5 | B21: 46085 | C21: 46098 | D21: Team 4 | E21: March | G21: 3.6 | H21: 3.5 | I21: 2.6 | J21: 5.1
A22: Sprint 6 | B22: 46099 | C22: 46112 | D22: Team 1 | E22: March | G22: 3.1 | H22: 1.4 | I22: 1 | J22: 4.6
A23: Sprint 6 | B23: 46099 | C23: 46112 | D23: Team 2 | E23: March | G23: 4.1 | H23: 3.8 | I23: 1.13 | J23: 5.23
A24: Sprint 6 | B24: 46099 | C24: 46112 | D24: Team 3 | E24: March | G24: 5.23 | H24: 6.2 | I24: 0.65 | J24: 7.2
A25: Sprint 6 | B25: 46099 | C25: 46112 | D25: Team 4 | E25: March | G25: 4.2 | H25: 3.3 | I25: 3.8 | J25: 7.1
A26: Q2 Sprint 1 | B26: 46113 | C26: 46126 | D26: Team 1 | E26: April | G26: 4.3 | H26: 1.3 | I26: 0.2 | J26: 4.17
A27: Q2 Sprint 1 | B27: 46113 | C27: 46126 | D27: Team 2 | E27: April | G27: 6.1 | H27: 4.1 | I27: 2.1 | J27: 8.2
A28: Q2 Sprint 1 | B28: 46113 | C28: 46126 | D28: Team 3 | E28: April | G28: 5.1 | H28: 3.1 | I28: 1.4 | J28: 4.17
A29: Q2 Sprint 1 | B29: 46113 | C29: 46126 | D29: Team 4 | E29: April | G29: 1.1 | H29: 1.2 | I29: 1.2 | J29: 2.2
... A34: Q2 Sprint 3 | B34: 46141 | C34: 46154 | D34: Team 1 | E34: May | G34: 3.2 | H34: 1.1 | I34: 1.1 | J34: 5.2
A35: Q2 Sprint 3 | B35: 46141 | C35: 46154 | D35: Team 2 | E35: May | G35: 6 | H35: 2.5 days | I35: 3.1 | J35: 6 days
A36: Q2 Sprint 3 | B36: 46141 | C36: 46154 | D36: Team 3 | E36: May | G36: 4.2 | H36: 4.3 | I36: 1.2 | J36: 4.2
A37: Q2 Sprint 3 | B37: 46141 | C37: 46154 | D37: Team 4 | E37: May | G37: 0.2 | H37: 2.1 | I37: 1.2 | J37: 3.1
A38: Q2 Sprint 4 | B38: 46155 | C38: 46168 | D38: Team 1 | E38: May | G38: 5.2 | H38: 1.4 | I38: 0.15 | J38: 5.2
A39: Q2 Sprint 4 | B39: 46155 | C39: 46168 | D39: Team 2 | E39: May | G39: 2.15 | H39: 1.22 | I39: 3.43 | J39: 2.18
A40: Q2 Sprint 4 | B40: 46155 | C40: 46168 | D40: Team 3 | E40: May | G40: 7.2 | H40: 3.6 | I40: 0.25 | J40: 7.13
A41: Q2 Sprint 4 | B41: 46155 | C41: 46168 | D41: Team 4 | E41: May | G41: 2.4 | H41: 1.12 | I41: 1 | J41: 6.7
A42: Q2 Sprint 5 | B42: 46169 | C42: 46182 | D42: Team 1 | E42: June | G42: 3.7 | H42: 1.9 | I42: 0.2 | J42: 5.1
A43: Q2 Sprint 5 | B43: 46169 | C43: 46182 | D43: Team 2 | E43: June | G43: 6.1 days | H43: 5.1 days | I43: 1.1 days | J43: 7.15 days
A44: Q2 Sprint 5 | B44: 46169 | C44: 46182 | D44: Team 3 | E44: June | G44: 7.5 days | H44: 2.1 days | I44: 1.2 days | J44: 7.2 days
A45: Q2 Sprint 5 | B45: 46169 | C45: 46182 | D45: Team 4 | E45: June | G45: 3.22 days | H45: 2.3 days | I45: 1.7 days | J45: 9.17 days
A46: Q2 Sprint 6 | B46: 46183 | C46: 46196 | D46: Team 1 | E46: June | G46: 3 | H46: 1.15 | I46: 0.13 | J46: 4.2
A47: Q2 Sprint 6 | B47: 46183 | C47: 46196 | D47: Team 2 | E47: June | G47: 4.3 | H47: 1.9 | I47: 0.11 | J47: 6.2
A48: Q2 Sprint 6 | B48: 46183 | C48: 46196 | D48: Team 3 | E48: June | G48: 4.2 | H48: 4 | I48: 4.4 | J48: 7.16
A49: Q2 Sprint 6 | B49: 46183 | C49: 46196 | D49: Team 4 | E49: June | G49: 13.21 | H49: 1.1 | I49: 1 | J49: 23

Sheet FTPR
A1: First Time Pass Rate
A2: Sprint ID | B2: Team | C2: Sprint Start Date | D2: Sprint End Date | E2: Month | F2: Total Stories Completed | G2: Total Stories Completed with Defects | H2: Total Stories Completed w/o any Defects | I2: FTPR | J2: Stories number having defects (1 or more)
A3: Sprint 6 | B3: Team 1 | C3: 46099 | D3: 46112 | E3: March | F3: 30 | G3: 3 | H3: 27 | I3: =H3/F3*100 -> 90 | J3: LIFE-21009,LIFE-21019,LIFE-24870
A4: Sprint 6 | B4: Team 2 | C4: 46099 | D4: 46112 | E4: March | F4: 18 | G4: 4 | H4: 14 | I4: =H4/F4*100 -> 77.777778 | J4: LIFE-26359,LIFE-26114,LIFE-25622,LIFE-24871
A5: Sprint 6 | B5: Team 3 | C5: 46099 | D5: 46112 | E5: March | F5: 8 | G5: 2 | H5: 6 | I5: =H5/F5*100 -> 75 | J5: LIFE-26840,LIFE-25711
A6: Sprint 6 | B6: Team 4 | C6: 46099 | D6: 46112 | E6: March | F6: 21 | G6: 1 | H6: 20 | I6: =H6/F6*100 -> 95.238095 | J6: LIFE-26564
A7: Sprint 5 | B7: Team 1 | C7: 46085 | D7: 46098 | E7: March | F7: 53 | G7: 10 | H7: 43 | I7: =H7/F7*100 -> 81.132075 | J7: LIFE-17329,LIFE-17374,LIFE-17449,LIFE-21003,LIFE-21021,LIFE-21998,LIFE-24407,LIFE-25566,LIFE-25612,LIFE-26159,
A8: Sprint 5 | B8: Team 2 | C8: 46085 | D8: 46098 | E8: March | F8: 17 | G8: 3 | H8: 14 | I8: =H8/F8*100 -> 82.352941 | J8: LIFE-25829,LIFE-25840,LIFE-26259
A9: Sprint 5 | B9: Team 3 | C9: 46085 | D9: 46098 | E9: March | F9: 11 | G9: 1 | H9: 10 | I9: =H9/F9*100 -> 90.909091 | J9: LIFE-22140
A10: Sprint 5 | B10: Team 4 | C10: 46085 | D10: 46098 | E10: March | F10: 17 | G10: 0 | H10: 17 | I10: =H10/F10*100 -> 100
A11: Q2 Sprint 1 | B11: Team 1 | C11: 46113 | D11: 46126 | E11: April | F11: 45 | G11: 22 | H11: 23 | I11: =H11/F11*100 -> 51.111111 | J11: LIFE-6512,LIFE-8983,LIFE-21016,LIFE-21011,LIFE-22466,LIFE-23241,LIFE-23687,LIFE-23719,LIFE-23740,LIFE-23765,LIFE-23914,LIFE-23921,LIFE-24028,LIFE-24077
A12: Q2 Sprint 1 | B12: Team 2 | C12: 46113 | D12: 46126 | E12: April | F12: 24 | G12: 7 | H12: 17 | I12: =H12/F12*100 -> 70.833333 | J12: LIFE-27961,LIFE-27233,LIFE-25859,LIFE-25082,LIFE-25078,LIFE-24556,LIFE-24343,LIFE-24078
A13: Q2 Sprint 1 | B13: Team 3 | C13: 46113 | D13: 46126 | E13: April | F13: 17 | G13: 0 | H13: 17 | I13: =H13/F13*100 -> 100
A14: Q2 Sprint 1 | B14: Team 4 | C14: 46113 | D14: 46126 | E14: April | F14: 33 | G14: 1 | H14: 32 | I14: =H14/F14*100 -> 96.969697 | J14: LIFE-26649
A15: Q2 Sprint 2 | B15: Team 1 | C15: 46127 | D15: 46140 | E15: April | F15: 16 | G15: 4 | H15: 12 | I15: =H15/F15*100 -> 75 | J15: LIFE-26681,LIFE-25824, LIFE-25119, LIFE-6757
A16: Q2 Sprint 2 | B16: Team 2 | C16: 46127 | D16: 46140 | E16: April | F16: 30 | G16: 3 | H16: 27 | I16: =H16/F16*100 -> 90 | J16: LIFE-26125, LIFE-25549, LIFE-24988
A17: Q2 Sprint 2 | B17: Team 3 | C17: 46127 | D17: 46140 | E17: April | F17: 7 | G17: 0 | H17: 7 | I17: =H17/F17*100 -> 100
A18: Q2 Sprint 2 | B18: Team 4 | C18: 46127 | D18: 46140 | E18: April | F18: 20 | G18: 0 | H18: 20 | I18: =H18/F18*100 -> 100
A19: Q2 Sprint 3 | B19: 46141 | C19: 46154 | D19: Team 1 | E19: May | F19: 14 | G19: 3 | H19: 11 | I19: =H19/F19*100 -> 78.571429 | J19: LIFE-25820,LIFE-22849,LIFE-22848
A20: Q2 Sprint 3 | B20: 46141 | C20: 46154 | D20: Team 2 | E20: May | F20: 48 | G20: 17 | H20: 31 | I20: =H20/F20*100 -> 64.583333 | J20: LIFE-26956,LIFE-27035,LIFE-24719,LIFE-26957,LIFE-28229,LIFE-26764,LIFE-19690,LIFE-18830,LIFE-27096,LIFE-26958,LIFE-26765,LIFE-26756,LIFE-26763,LIFE-15809,LIFE-26767,LIFE-28532,LIFE-15801
A21: Q2 Sprint 3 | B21: 46141 | C21: 46154 | D21: Team 3 | E21: May | F21: 15 | G21: 2 | H21: 13 | I21: =H21/F21*100 -> 86.666667 | J21: LIFE-26869,LIFE-6861
A22: Q2 Sprint 3 | B22: 46141 | C22: 46154 | D22: Team 4 | E22: May | F22: 30 | G22: 2 | H22: 28 | I22: =H22/F22*100 -> 93.333333 | J22: LIFE-28965,LIFE-27172
A23: Q2 Sprint 4 | B23: 46155 | C23: 46168 | D23: Team 1 | E23: May | F23: 28 | G23: 3 | H23: 25 | I23: =H23/F23*100 -> 89.285714 | J23: LIFE-24349,LIFE-24345,LIFE-6758
A24: Q2 Sprint 4 | B24: 46155 | C24: 46168 | D24: Team 2 | E24: May | F24: 29 | G24: 6 | H24: 23 | I24: =H24/F24*100 -> 79.310345 | J24: LIFE-29960,LIFE-29957,LIFE-29952,LIFE-28976,LIFE-26957,LIFE-19690
A25: Q2 Sprint 4 | B25: 46155 | C25: 46168 | D25: Team 3 | E25: May | F25: 4 | G25: 0 | H25: 4 | I25: =H25/F25*100 -> 100
A26: Q2 Sprint 4 | B26: 46155 | C26: 46168 | D26: Team 4 | E26: May | F26: 12 | G26: 0 | H26: 12 | I26: =H26/F26*100 -> 100
A27: Q2 Sprint 5 | B27: 46169 | C27: 46182 | D27: Team 1 | E27: June | F27: 25 | G27: 8 | H27: 17 | I27: =H27/F27*100 -> 68 | J27: LIFE-31123,LIFE-30286,LIFE-27867,LIFE-26040,LIFE-25822,LIFE-25113,LIFE-24734,LIFE-24361
A28: Q2 Sprint 5 | B28: 46169 | C28: 46182 | D28: Team 2 | E28: June | F28: 35 | G28: 12 | H28: 23 | I28: =H28/F28*100 -> 65.714286 | J28: LIFE-29958,LIFE-29956,LIFE-29954,LIFE-29504,LIFE-29499,LIFE-29497,LIFE-28320,LIFE-28314,LIFE-26956,LIFE-26555,LIFE-26119,LIFE-23970
A29: Q2 Sprint 5 | B29: 46169 | C29: 46182 | D29: Team 3 | E29: June | F29: 12 | G29: 1 | H29: 11 | I29: =H29/F29*100 -> 91.666667 | J29: LIFE-20339
A30: Q2 Sprint 5 | B30: 46169 | C30: 46182 | D30: Team 4 | E30: June | F30: 30 | G30: 0 | H30: 30 | I30: =H30/F30*100 -> 100
A31: Q2 Sprint 6 | B31: 46183 | C31: 46196 | D31: Team 1 | E31: June | F31: 17 | G31: 3 | H31: 14 | I31: =H31/F31*100 -> 82.352941 | J31: LIFE-25776,LIFE-22847,LIFE-19604
A32: Q2 Sprint 6 | B32: 46183 | C32: 46196 | D32: Team 2 | E32: June | F32: 16 | G32: 5 | H32: 11 | I32: =H32/F32*100 -> 68.75 | J32: LIFE-29941,LIFE-27038,LIFE-25022,LIFE-24997,LIFE-17126
A33: Q2 Sprint 6 | B33: 46183 | C33: 46196 | D33: Team 3 | E33: June | F33: 7 | G33: 1 | H33: 6 | I33: =H33/F33*100 -> 85.714286 | J33: LIFE-31334
A34: Q2 Sprint 6 | B34: 46183 | C34: 46196 | D34: Team 4 | E34: June | F34: 20 | G34: 0 | H34: 20 | I34: =H34/F34*100 -> 100

Sheet Backlog
A1: Backlog Summary
A2: Team | B2: EPIC | C2: Release | D2: Feature | E2: Total Stories | F2: Total Story Points | G2: Groomed | H2: Spike | I2: Notes
A3: Team 1 | B3: Prod-199 | C3: June

Sheet EAC Notes
B2: Monthly burn variance shows how we performed financially this month, while Estimate at Completion shows where we are projected to land financially at the end of the program.
B3: EAC = Money already spent + Forecast remaining cost
B4: Example Item Amount Spent so far $2.5M Remaining forecast $2.8M EAC $5.3M
B5: Usually caused by: rework poor estimation scope creep low productivity
B7: EAC tells leadership: ✅ Is the vendor financially under control? ✅ Will we overspend before project ends? ✅ Are estimates realistic? ✅ Is scope or rework increasing cost? It is a forward-looking health indicator.

Sheet Disussion Points
A2: Metrics | B2: Inputs
A3: ETC | B3: Refined backlog for next 1 quarter
A4: Cost per SP | B4: How to calculate cost for ERIE and Innova for overall ETC and cost per sprint/point
A5: Rework effort | B5: Assign points/complexity to defect to determine ave rework effort
A6: Cycle Time (Median) | B6: Establish baseline from JIRA for SP1, SP2 etc

Sheet Monthly Burn Variance Reasons
A1: Monthly Cost Variance
A3: Category
A4: Rework
A5: Depedency Delay
A6: Scope Changes
A7: Staffing

Sheet Risks_Decisions_Improvements
A1: Date | B1: Category | C1: Details | D1: Updates | E1: Owner | F1: ETA | G1: Status
A2: 46176 | B2: Improvement | C2: QA team cross skilling across all the sprint teams | D2: QA team got trained in Illustration/Premium/Pricing Testing/Uwpro/Downstream Batch processing/Billing and other relevant topics
A3: 46154 | B3: Improvement | C3: Complete the Applitool Scripts for automatic regression of the forms | D3: 14 Scripts are prepared and run to support the Release 1.1 | E3: Ashish/Veera/Ananth | F3: 46161 | G3: Completed
A4: 46147 | B4: Improvement | C4: Implement a formal and manually gated print code review process | D4: Nowsheen is leading the Print code review with support from Melinda and CK. | E4: Nowsheen | F4: 46154 | G4: Completed
A5: 46147 | B5: Improvement | C5: Plan for In-Sprint automation for missed story cards from past sprints - Team 1 and Team 3 for Release 1.1 | D5: Team 1 (2 Hours) LIFE-28764 - LifeWeb - Other Insurance and Replacement Screen - 1st Question Displayed Incorrectly LIFE-28410- Other Insurance and Replacement Screen - New Question Team 3 (2 hours) LIFE-27290- Taxonomy Changes - EFL Money to EFL Billing | E5: Manish/Arun/Karthik/Joy | F5: 46154 | G5: Completed
A6: 46150 | B6: Improvement | C6: First time pass rate has been consistently low specially for team 1 and team 2. | D6: Need to strengthen the process - pre-amigo, smaller story cards etc. this will be an ongoing activity unless we see improve FTPR to 95% | E6: Karthik/Melinda/Abhijit | F6: 46203 | G6: WIP
A7: 46147 | B7: Improvement | C7: Provided 212 UAT policies (60 policies premium testing, 60 policies commission, 65 policies Dade pay testing, 12 portal testing, 15 forms content validation testing) to business team so far that would have taken at least 70 hours (20 mins/per policy) | E7: Ashish/Veera/Ananth | F7: Ongoing | G7: WIP
A8: 46192 | B8: Decision | C8: Pavan Bhubathiraju ( Integration Developer) Role Closure | D8: Pavan has worked only on couple of cards in last few sprints. He is also aspiring to move onto other areas of work. We believe he is not being fully utilized and the role can be closed | E8: Joy/Nick | F8: 46206 | G8: WIP
A9: 46191 | B9: Decision | C9: Progressing with the agreed Addendum | D9: Its discussed and shared over email | E9: Joy | F9: 46199 | G9: Completed
A10: 46195 | B10: Decision | C10: Approval to have Sandip Banala as Vaishnavi's replacement as Sadhu Dharani as Mendix buffer in the team | D10: Vaishnavi has resigned last week | E10: Joy | F10: 46199 | G10: Completed
A11: 46176 | B11: Decision | C11: Need a decision on Shivani Yandra's billability - she was supposed to replacement for Sushanth Merugu and join team 1. SVP Approval pending since 4/27 | D11: Chrystal following up with Joy | E11: Joy/Nick/Subrata | F11: 46178 | G11: Completed
A12: 46120 | B12: Decision | C12: Raja, Bharat and Subbu are planned to be released by 6/28 per SOW. With full rollout moving to June and we expect some enhancement post rollout so do we expect to extend their contract? We may have to extend it until Q3 for Subbu/Bharat and end of year for Raja? | D12: Subbu can be roll off. 6/24 Final Expense, 6/18 Reinstatement, 6/4 Wholelife, 7/16 - Misc, Conversion - Tentative Sept. Karthik/Joy to connect and come back for Bharat by 5/22. Raja to keep it until end of Sept. | E12: Joy/Karthik | F12: 46164 | G12: Open
A13: 46106 | B13: Decision | C13: Improve collaboration and partnership with Sapiens team. Avoid escalation unless absolutely necessary. Document has been put in place | D13: Joy informed Brian that QA will put note in Sapiens Defect if anything is missing to avoid any concern. All QA's are part of Sapiens call. Pending Item - File testing is in progress so learning curve will be there while running new batches. | E13: Nick/Joy | F13: 46106 | G13: Closed
A14: 46106 | B14: Decision | C14: Moving code to Test PS for term as most of the term work was completed to continue with downstream validation because of active development in Test A for whole life/re-instatement and uncovering unexpected blockers | D14: Term code moved to Test PS | E14: Melinda/Karthik/Joy | F14: 46115 | G14: Closed
A15: 46106 | B15: Decision | C15: Team 1 assign story points to standalone defects to determine the effort but other teams don’t follow this and keep 0 points. We need alignment and determine the consistent approach across teams | D15: Joy will work with all Scrum Masters on this | E15: Joy | G15: Closed
A16: 46106 | B16: Decision | C16: Should team look at baseline velocity vs total points planned for Sprint Commitment? | D16: Team aligned to use baseline velocity for sprint commitment | E16: Joy | F16: 46106 | G16: Closed
A17: 46176 | B17: Risk | C17: Down times due to and following Sapiens Deployment are impacting hours of Testing Window ( e.g., 5/27, 5/29, 6/1) | D17: Enforce a more robust smoke testing and shorter deployment window for Sapiens | E17: Corey/Joy | F17: 46188 | G17: Open
A18: 46161 | B18: Risk | C18: The bi-weekly release cycle since term pilot is creating conflicting capacity prioritization between in-sprint work ( Full roll-out,whole life , reinstatement etc), Defect retests for release cycles, whole life E2E plan, E2E execution and regression cycles for the release & UAT support and in sprint automation effort. This can potentially slow down the progress to whole life and full-roll out | D18: Team assessing the possibility of bringing in more automation in regression. Also discuss the risk with Erie Leadership for possible options and approaches | E18: Arun/Karthik/Joy/Nick | F18: TBD | G18: WIP
A19: 46161 | B19: Risk | C19: Frequently different versions of CoreSuite codes between Test and Prod and even within Test environment through different periods of Testing due to the weekly release schedule potentially blocking or slowing down the Regression activities and reducing the integrity of the testing | D19: Corey is working with Sapiens on the release roadmap | E19: Corey/Karthik | F19: TBD | G19: WIP
A20: 46120 | B20: Risk | C20: Downstream testing, file testing, and PHS testing are at risk due to automated batches not yet enabled in TestPS | D20: Meeting is being setup with PPS to automate batches at the earliest | E20: Corey/Manish | F20: 46126 | G20: Closed
A21: 46106 | B21: Risk | C21: known Risk - Whole life Sapiens cards/defects are planned for 4/20 (Sprint 12) release putting risk for pilot. | D21: Team decided to move forward with Term only for pilot so we are good | E21: Joy/Nick | F21: 46113 | G21: Closed
A22: 46106 | B22: Risk | C22: Known Risk - About 25+ interface files to be validated part of E2E - File development (3 CRs + Infogix) pending with Sapiens needed for pilot and rest files need to be tested/validated by business | D22: Corey is setting up time with business/QA for working session for pending validation files and Joy following up with Sapiens for the update | E22: Joy/Corey/Manish/Karthik | G22: Closed
A23: 46106 | B23: Risk | C23: Unexpected downtime impacting E2E testing (Sapiens, UWPro, Tempus etc) being tracked and actions are being taken | D23: This will be ongoing tracking to notice any unplanned outage and take actions | E23: Manish/Karthik/Melinda/Arun | G23: Closed
A24: 46120 | B24: Improvement | C24: Automation Handbook drafting is in progress | D24: keeping the completion date as 4/17 to include API part and code movement/branching/approval process | E24: Ashish/Bharat/Karthik | F24: 46157 | G24: WIP
A25: 46120 | B25: Improvement | C25: Started 5 why analysis to reduce the rework ratio for SP6 defects. Expecting the action to be taken that helps to reduce the rework effort | E25: Karthik/Melinda/Manish/Arun | F25: Ongoing | G25: WIP
A26: 46120 | B26: Improvement | C26: Working with Melinda to generate data models (Logical/Physical) for AWS purge project | D26: Initial results are shared with Manoj. Review and refinement may be needed after the review. | E26: Melinda/Manoj | F26: 46126 | G26: Completed
A27: 46106 | B27: Improvement | C27: Both UI and API smoke/regression suites are scheduled daily (Test A/Test PS) to track and reason for failure | E27: Ashish/Bharat | G27: Completed
A28: 46106 | B28: Improvement | C28: Improvement in Automation code quality and stability as team updated the code to the new framework version and fixed the issues. | E28: Ashish | G28: Completed
A29: 46106 | B29: Improvement | C29: Improving quality by enabling gated (30%) pipeline for Test A/PS | D29: Seeing about 60% pass rate past few build in TestPS. | E29: Karthik/Ashish/Melinda/Mateen | F29: 46108 | G29: Completed
A30: 46120 | B30: Improvement | C30: QA Team completed ChatGPT pilot for test case design with Team 2 with the help of Karthik and noticed 30% estimated design savings. | D30: Implementation is in progress for Team 2 story cards to see the efficiency and saving at scale | E30: Manish/Arun/Karthik | F30: 46122 | G30: Completed
A31: 46106 | B31: Improvement | C31: Daily testing report involve lot of manual effort, prone to error. Looking for semi-automate the report in JIRA | D31: Planned for Release 1.1 | E31: Purush | G31: WIP
A32: 46106 | B32: Decision | C32: Explore and plan ahead on tentative card delivery dates across teams by Developers to avoid spillover | E32: Melinda/Joy | G32: TBD
A33: 46106 | B33: Improvement | C33: Strong overlap between Onsite and Offshore served us well in the winter, many supported late EST afternoon for direct interaction with ERIE | E33: Arunava/Manish | G33: Completed
A34: 46106 | B34: Improvement | C34: Frequent connect is in place with ERIE leads (Abhishek, Karthik, Melinda, Abhijit) for concern, feedback and improvement | E34: Manish/Arun | G34: Completed

Sheet Prod Leakage Details
A1: Release | B1: Problem | C1: Impact | D1: Urgency | E1: Priority | F1: Description | G1: Root cause | H1: Action Item
A2: March'26 | B2: PRB0068481 | C2: Low | D2: Medium | E2: 4-Low | F2: Inflight scenarios failed in Prod | G2: code fix was made to conversion which had impact to new business flow but impact analysis was not done so inflight NB scenarios were not re-executed | H2: Developer/QA work together end of testing, review defects, perform impact analysis and plan the manual regression along with automated regression
A3: March'26 | B3: PRB0068596 | C3: Low | D3: Low | E3: 5-Planning | F3: non-life agent able to issue EEL policy | G3: Service change (MDM to ASR) - Code was copied from TUW but didn’t have unit test cases covered and understanding of the scope/code | H3: Non-life agent testing will be added part of regression for every release
A4: March'26 | B4: PRB0068645 | C4: Medium | D4: Low | E4: 4-Low | F4: Error for Life License (Recent release issue to update a constant missed) | G4: MDM pointing to Stage instead of prod (constant/env change) but was not added in the dev checklist | H4: TBD
A6: Please refer to the Quality tab post March data
